{"1":[{"players":4,"id":"66032","platform":"ps4","main_video":"https:\/\/youtu.be\/SQRCI7igZkk","video_id":"SQRCI7igZkk","video_type":"youtube","unit":"Round","format":null,"note":null,"added":"12th, March 2021","other_links":null,"achieved":"44","player1":{"id":"19189","name":"ZKL_allstargamer ","flag":"france","cheater":"0","banned":"0","url":"\/players\/WktMX2FsbHN0YXJnYW1lciA\/","staff_role":null,"staff_enabled":null,"staff_hidden":null},"player2":{"id":"15356","name":"ZKL_Momo","flag":"france","cheater":"0","banned":"0","url":"\/players\/WktMX01vbW8\/","staff_role":null,"staff_enabled":null,"staff_hidden":null},"player3":{"id":"9603","name":"LTK_Jubo","flag":"belgium","cheater":"0","banned":"0","url":"\/players\/TFRLX0p1Ym8\/","staff_role":null,"staff_enabled":null,"staff_hidden":null},"player4":{"id":"17445","name":"LTK_Marsou_67","flag":"france","cheater":"0","banned":"0","url":"\/players\/TFRLX01hcnNvdV82Nw\/","staff_role":null,"staff_enabled":null,"staff_hidden":null},"rank":1}],"2":[{"players":4,"id":"41996","platform":"ps4","main_video":"https:\/\/www.youtube.com\/watch?v=sVtsqBLyUFQ","video_id":"sVtsqBLyUFQ","video_type":"youtube","unit":"Round","format":null,"note":null,"added":"28th, October 2019","other_links":null,"achieved":"41","player1":{"id":"12417","name":"BAN MY XB0X","flag":"usa","cheater":"0","banned":"0","url":"\/players\/QkFOIE1ZIFhCMFg\/","staff_role":null,"staff_enabled":null,"staff_hidden":null},"player2":{"id":"14548","name":"Cod---side","flag":"usa","cheater":"0","banned":"0","url":"\/players\/Q29kLS0tc2lkZQ\/","staff_role":null,"staff_enabled":null,"staff_hidden":null},"player3":{"id":"2269","name":"dtpuka98","flag":"usa","cheater":"0","banned":"0","url":"\/players\/ZHRwdWthOTg\/","staff_role":null,"staff_enabled":null,"staff_hidden":null},"player4":{"id":"2874","name":"Spykes27","flag":"trinidad","cheater":"0","banned":"0","url":"\/players\/U3B5a2VzMjc\/","staff_role":null,"staff_enabled":null,"staff_hidden":null},"rank":2}],"3":[{"players":4,"id":"33385","platform":"ps4","main_video":"https:\/\/youtu.be\/kIQ9X_woC3Y","video_id":"kIQ9X_woC3Y","video_type":"youtube","unit":"Round","format":null,"note":null,"added":"1st, February 2019","other_links":null,"achieved":"37","player1":{"id":"16692","name":"Manouchkov71","flag":"france","cheater":"0","banned":"0","url":"\/players\/TWFub3VjaGtvdjcx\/","staff_role":null,"staff_enabled":null,"staff_hidden":null},"player2":{"id":"19816","name":"Komodoydx","flag":"france","cheater":"0","banned":"0","url":"\/players\/S29tb2RveWR4\/","staff_role":null,"staff_enabled":null,"staff_hidden":null},"player3":{"id":"1039","name":"AP_DarylBye","flag":"france","cheater":"0","banned":"0","url":"\/players\/QVBfRGFyeWxCeWU\/","staff_role":null,"staff_enabled":null,"staff_hidden":null},"player4":{"id":"15207","name":"ProZ-YTB__FortNikeur","flag":"france","cheater":"0","banned":"0","url":"\/players\/UHJvWi1ZVEJfX0ZvcnROaWtldXI\/","staff_role":null,"staff_enabled":null,"staff_hidden":null},"rank":3}],"4":[{"players":4,"id":"31968","platform":"xb1","main_video":"https:\/\/www.youtube.com\/watch?v=ehzVmmldcW0","video_id":"ehzVmmldcW0","video_type":"youtube","unit":"Round","format":null,"note":null,"added":"3rd, December 2018","other_links":null,"achieved":"35","player1":{"id":"12417","name":"BAN MY XB0X","flag":"usa","cheater":"0","banned":"0","url":"\/players\/QkFOIE1ZIFhCMFg\/","staff_role":null,"staff_enabled":null,"staff_hidden":null},"player2":{"id":"12739","name":"HollowCross","flag":"usa","cheater":"0","banned":"0","url":"\/players\/SG9sbG93Q3Jvc3M\/","staff_role":null,"staff_enabled":null,"staff_hidden":null},"player3":{"id":"5310","name":"DrewDripper","flag":"usa","cheater":"0","banned":"0","url":"\/players\/RHJld0RyaXBwZXI\/","staff_role":null,"staff_enabled":null,"staff_hidden":null},"player4":{"id":"16207","name":"Aquire Bands","flag":"usa","cheater":"0","banned":"0","url":"\/players\/QXF1aXJlIEJhbmRz\/","staff_role":null,"staff_enabled":null,"staff_hidden":null},"rank":4}],"5":[{"players":4,"id":"31926","platform":"ps4","main_video":"https:\/\/www.twitch.tv\/videos\/343614116","video_id":"343614116","video_type":"twitch","unit":"Round","format":null,"note":null,"added":"2nd, December 2018","other_links":null,"achieved":"25","player1":{"id":"652","name":"WLR51sang","flag":"france","cheater":"0","banned":"0","url":"\/players\/V0xSNTFzYW5n\/","staff_role":null,"staff_enabled":null,"staff_hidden":null},"player2":{"id":"10465","name":"LopezLoic","flag":"france","cheater":"0","banned":"0","url":"\/players\/TG9wZXpMb2lj\/","staff_role":null,"staff_enabled":null,"staff_hidden":null},"player3":{"id":"16182","name":"PurpleHaze1326","flag":"france","cheater":"0","banned":"0","url":"\/players\/UHVycGxlSGF6ZTEzMjY\/","staff_role":null,"staff_enabled":null,"staff_hidden":null},"player4":{"id":"16183","name":"Pilou0212","flag":"france","cheater":"0","banned":"0","url":"\/players\/UGlsb3UwMjEy\/","staff_role":null,"staff_enabled":null,"staff_hidden":null},"rank":5}],"6":[{"players":4,"id":"31746","platform":"ps4","main_video":"https:\/\/m.youtube.com\/watch?v=ZnOyvE3591A","video_id":"ZnOyvE3591A","video_type":"youtube","unit":"Round","format":null,"note":null,"added":"25th, November 2018","other_links":null,"achieved":"16","player1":{"id":"16063","name":"FaZe_Archeive","flag":"usa","cheater":"0","banned":"0","url":"\/players\/RmFaZV9BcmNoZWl2ZQ\/","staff_role":null,"staff_enabled":null,"staff_hidden":null},"player2":{"id":"16064","name":"Diyull","flag":"usa","cheater":"0","banned":"0","url":"\/players\/RGl5dWxs\/","staff_role":null,"staff_enabled":null,"staff_hidden":null},"player3":{"id":"16065","name":"PenguinKiller115","flag":"usa","cheater":"0","banned":"0","url":"\/players\/UGVuZ3VpbktpbGxlcjExNQ\/","staff_role":null,"staff_enabled":null,"staff_hidden":null},"player4":{"id":"16066","name":"Likeaboss1234220","flag":"usa","cheater":"0","banned":"0","url":"\/players\/TGlrZWFib3NzMTIzNDIyMA\/","staff_role":null,"staff_enabled":null,"staff_hidden":null},"rank":6}],"7":[{"players":4,"id":"31009","platform":"ps4","main_video":"https:\/\/youtu.be\/0nRrDpmZY4E","video_id":"0nRrDpmZY4E","video_type":"youtube","unit":"Round","format":null,"note":null,"added":"8th, November 2018","other_links":null,"achieved":"12","player1":{"id":"15591","name":"i_CxReY--","flag":"england","cheater":"0","banned":"0","url":"\/players\/aV9DeFJlWS0t\/","staff_role":null,"staff_enabled":null,"staff_hidden":null},"player2":{"id":"15592","name":"SJM-_-ELITE","flag":"england","cheater":"0","banned":"0","url":"\/players\/U0pNLV8tRUxJVEU\/","staff_role":null,"staff_enabled":null,"staff_hidden":null},"player3":{"id":"15593","name":"geniusdp200","flag":"england","cheater":"0","banned":"0","url":"\/players\/Z2VuaXVzZHAyMDA\/","staff_role":null,"staff_enabled":null,"staff_hidden":null},"player4":{"id":"15594","name":"Saiffazli101","flag":"england","cheater":"0","banned":"0","url":"\/players\/U2FpZmZhemxpMTAx\/","staff_role":null,"staff_enabled":null,"staff_hidden":null},"rank":7}]}