{"1":[{"players":2,"id":"95317","platform":"xb1","main_video":"https:\/\/www.twitch.tv\/videos\/1580479670","video_id":"1580479670","video_type":"twitch","unit":"Round","format":null,"note":null,"added":"3rd, September 2022","other_links":null,"achieved":"34","player1":{"id":"921585","name":"CruspySpine","flag":"italy","cheater":"0","banned":"0","url":"\/players\/Q3J1c3B5U3BpbmU\/","staff_role":null,"staff_enabled":null,"staff_hidden":null},"player2":{"id":"17767","name":"EazyRandeazy","flag":"usa","cheater":"0","banned":"0","url":"\/players\/RWF6eVJhbmRlYXp5\/","staff_role":null,"staff_enabled":null,"staff_hidden":null},"rank":1}],"2":[{"players":2,"id":"55494","platform":"ps4","main_video":"https:\/\/www.youtube.com\/watch?v=3iLZFpYCSEc","video_id":"3iLZFpYCSEc","video_type":"youtube","unit":"Round","format":null,"note":null,"added":"24th, May 2020","other_links":null,"achieved":"29","player1":{"id":"920264","name":"Mchappivajari","flag":"finland","cheater":"0","banned":"0","url":"\/players\/TWNoYXBwaXZhamFyaQ\/","staff_role":null,"staff_enabled":null,"staff_hidden":null},"player2":{"id":"920284","name":"MakeMoottorisaha","flag":"finland","cheater":"0","banned":"0","url":"\/players\/TWFrZU1vb3R0b3Jpc2FoYQ\/","staff_role":null,"staff_enabled":null,"staff_hidden":null},"rank":2}],"3":[{"players":2,"id":"23257","platform":"pc","main_video":"https:\/\/www.youtube.com\/watch?v=NrGQhB5p_Y8&t=14s","video_id":"NrGQhB5p_Y8","video_type":"youtube","unit":"Round","format":null,"note":null,"added":"22nd, November 2017","other_links":null,"achieved":"28","player1":{"id":"9962","name":"Flo203","flag":"france","cheater":"0","banned":"0","url":"\/players\/RmxvMjAz\/","staff_role":null,"staff_enabled":null,"staff_hidden":null},"player2":{"id":"2478","name":"New_Stormz","flag":"belgium","cheater":"0","banned":"0","url":"\/players\/TmV3X1N0b3Jteg\/","staff_role":null,"staff_enabled":null,"staff_hidden":null},"rank":3},{"players":2,"id":"59426","platform":"ps4","main_video":"https:\/\/youtu.be\/ewNcgEWTPSs","video_id":"ewNcgEWTPSs","video_type":"youtube","unit":"Round","format":null,"note":null,"added":"7th, July 2020","other_links":null,"achieved":"28","player1":{"id":"18305","name":"j_ comber011","flag":"usa","cheater":"0","banned":"0","url":"\/players\/al8gY29tYmVyMDEx\/","staff_role":null,"staff_enabled":null,"staff_hidden":null},"player2":{"id":"919294","name":"AdD1cT3D2tWO","flag":"england","cheater":"0","banned":"0","url":"\/players\/QWREMWNUM0QydFdP\/","staff_role":null,"staff_enabled":null,"staff_hidden":null}}],"4":[{"players":2,"id":"24317","platform":"ps4","main_video":"https:\/\/www.twitch.tv\/videos\/229073330","video_id":"229073330","video_type":"twitch","unit":"Round","format":null,"note":null,"added":"15th, February 2018","other_links":null,"achieved":"27","player1":{"id":"216","name":"Guardurheart423","flag":"usa","cheater":"0","banned":"0","url":"\/players\/R3VhcmR1cmhlYXJ0NDIz\/","staff_role":null,"staff_enabled":null,"staff_hidden":null},"player2":{"id":"12219","name":"iLL_iZ_Ty","flag":"usa","cheater":"0","banned":"0","url":"\/players\/aUxMX2laX1R5\/","staff_role":null,"staff_enabled":null,"staff_hidden":null},"rank":4}],"5":[{"players":2,"id":"41664","platform":"xb1","main_video":"https:\/\/www.twitch.tv\/videos\/496508118","video_id":"496508118","video_type":"twitch","unit":"Round","format":null,"note":null,"added":"19th, October 2019","other_links":null,"achieved":"26","player1":{"id":"18868","name":"BaboNudel","flag":"germany","cheater":"0","banned":"0","url":"\/players\/QmFib051ZGVs\/","staff_role":null,"staff_enabled":null,"staff_hidden":null},"player2":{"id":"18869","name":"iPushFatPeople","flag":"germany","cheater":"0","banned":"0","url":"\/players\/aVB1c2hGYXRQZW9wbGU\/","staff_role":null,"staff_enabled":null,"staff_hidden":null},"rank":5}],"6":[{"players":2,"id":"28244","platform":"xb1","main_video":"www.twitch.tv\/videos\/297976801","video_id":"297976801","video_type":"twitch","unit":"Round","format":null,"note":null,"added":"16th, August 2018","other_links":null,"achieved":"24","player1":{"id":"13943","name":"OG Mr Crabs","flag":"usa","cheater":"0","banned":"0","url":"\/players\/T0cgTXIgQ3JhYnM\/","staff_role":null,"staff_enabled":null,"staff_hidden":null},"player2":{"id":"14049","name":"DYSR FuRy","flag":"usa","cheater":"0","banned":"0","url":"\/players\/RFlTUiBGdVJ5\/","staff_role":null,"staff_enabled":null,"staff_hidden":null},"rank":6}],"7":[{"players":2,"id":"24217","platform":"ps4","main_video":"https:\/\/youtu.be\/-AU4XalqZuw","video_id":"-AU4XalqZuw","video_type":"youtube","unit":"Round","format":null,"note":null,"added":"10th, February 2018","other_links":null,"achieved":"23","player1":{"id":"12500","name":"BeYsSs","flag":"france","cheater":"0","banned":"0","url":"\/players\/QmVZc1Nz\/","staff_role":null,"staff_enabled":null,"staff_hidden":null},"player2":{"id":"12527","name":"Fr-S_Flez93","flag":"france","cheater":"0","banned":"0","url":"\/players\/RnItU19GbGV6OTM\/","staff_role":null,"staff_enabled":null,"staff_hidden":null},"rank":7}],"8":[{"players":2,"id":"24072","platform":"xb1","main_video":"https:\/\/www.twitch.tv\/videos\/225383137","video_id":"225383137","video_type":"twitch","unit":"Round","format":null,"note":null,"added":"3rd, February 2018","other_links":null,"achieved":"21","player1":{"id":"6374","name":"xZeddyz","flag":"canada","cheater":"0","banned":"0","url":"\/players\/eFplZGR5eg\/","staff_role":null,"staff_enabled":null,"staff_hidden":null},"player2":{"id":"12479","name":"xTGx RedPanda","flag":"canada","cheater":"0","banned":"0","url":"\/players\/eFRHeCBSZWRQYW5kYQ\/","staff_role":null,"staff_enabled":null,"staff_hidden":null},"rank":8},{"players":2,"id":"28005","platform":"xb1","main_video":"www.twitch.tv\/videos\/294638264","video_id":"294638264","video_type":"twitch","unit":"Round","format":null,"note":null,"added":"8th, August 2018","other_links":null,"achieved":"21","player1":{"id":"13943","name":"OG Mr Crabs","flag":"usa","cheater":"0","banned":"0","url":"\/players\/T0cgTXIgQ3JhYnM\/","staff_role":null,"staff_enabled":null,"staff_hidden":null},"player2":{"id":"13945","name":"Im a Porg","flag":"usa","cheater":"0","banned":"0","url":"\/players\/SW0gYSBQb3Jn\/","staff_role":null,"staff_enabled":null,"staff_hidden":null}},{"players":2,"id":"51267","platform":"xb1","main_video":"https:\/\/www.youtube.com\/watch?v=7W6H7YTPEhU&feature=youtu.be","video_id":"7W6H7YTPEhU","video_type":"youtube","unit":"Round","format":null,"note":null,"added":"21st, April 2020","other_links":null,"achieved":"21","player1":{"id":"917746","name":"Zomb Phox","flag":"usa","cheater":"0","banned":"0","url":"\/players\/Wm9tYiBQaG94\/","staff_role":null,"staff_enabled":null,"staff_hidden":null},"player2":{"id":"918664","name":"ViperzzzLegacy","flag":"usa","cheater":"0","banned":"0","url":"\/players\/VmlwZXJ6enpMZWdhY3k\/","staff_role":null,"staff_enabled":null,"staff_hidden":null}},{"players":2,"id":"56854","platform":"ps4","main_video":"https:\/\/youtu.be\/yAPpswZo_P4?t=332","video_id":"yAPpswZo_P4","video_type":"youtube","unit":"Round","format":null,"note":null,"added":"8th, June 2020","other_links":null,"achieved":"21","player1":{"id":"920937","name":"arthoine845","flag":"france","cheater":"0","banned":"0","url":"\/players\/YXJ0aG9pbmU4NDU\/","staff_role":null,"staff_enabled":null,"staff_hidden":null},"player2":{"id":"920938","name":"Dendeh-_","flag":"france","cheater":"0","banned":"0","url":"\/players\/RGVuZGVoLV8\/","staff_role":null,"staff_enabled":null,"staff_hidden":null}}],"9":[{"players":2,"id":"23643","platform":"xb1","main_video":"https:\/\/www.twitch.tv\/videos\/206003093","video_id":"206003093","video_type":"twitch","unit":"Round","format":null,"note":null,"added":"17th, January 2018","other_links":null,"achieved":"19","player1":{"id":"1404","name":"checkka","flag":"usa","cheater":"0","banned":"0","url":"\/players\/Y2hlY2trYQ\/","staff_role":null,"staff_enabled":null,"staff_hidden":null},"player2":{"id":"1405","name":"gringoBEAN","flag":"usa","cheater":"0","banned":"0","url":"\/players\/Z3JpbmdvQkVBTg\/","staff_role":null,"staff_enabled":null,"staff_hidden":null},"rank":9},{"players":2,"id":"60333","platform":"ps4","main_video":"https:\/\/youtu.be\/poUKna2uq5k","video_id":"poUKna2uq5k","video_type":"youtube","unit":"Round","format":null,"note":null,"added":"19th, July 2020","other_links":null,"achieved":"19","player1":{"id":"13696","name":"IxI_Cinder_IxI","flag":"usa","cheater":"0","banned":"0","url":"\/players\/SXhJX0NpbmRlcl9JeEk\/","staff_role":null,"staff_enabled":null,"staff_hidden":null},"player2":{"id":"922548","name":"Its_DaFox69","flag":"usa","cheater":"0","banned":"0","url":"\/players\/SXRzX0RhRm94Njk\/","staff_role":null,"staff_enabled":null,"staff_hidden":null}}],"10":[{"players":2,"id":"34519","platform":"ps4","main_video":"https:\/\/youtu.be\/kOsCFPrE9Jc","video_id":"kOsCFPrE9Jc","video_type":"youtube","unit":"Round","format":null,"note":null,"added":"8th, April 2019","other_links":null,"achieved":"18","player1":{"id":"16938","name":"Zombie King","flag":"italy","cheater":"0","banned":"0","url":"\/players\/Wm9tYmllIEtpbmc\/","staff_role":null,"staff_enabled":null,"staff_hidden":null},"player2":{"id":"17217","name":"King Jack","flag":"italy","cheater":"0","banned":"0","url":"\/players\/S2luZyBKYWNr\/","staff_role":null,"staff_enabled":null,"staff_hidden":null},"rank":10}],"11":[{"players":2,"id":"24712","platform":"ps4","main_video":"https:\/\/youtu.be\/_9CHJ879WG8","video_id":"_9CHJ879WG8","video_type":"youtube","unit":"Round","format":null,"note":null,"added":"4th, March 2018","other_links":null,"achieved":"17","player1":{"id":"12742","name":"Dexy-5k","flag":"usa","cheater":"0","banned":"0","url":"\/players\/RGV4eS01aw\/","staff_role":null,"staff_enabled":null,"staff_hidden":null},"player2":{"id":"12743","name":"allhailme225","flag":"usa","cheater":"0","banned":"0","url":"\/players\/YWxsaGFpbG1lMjI1\/","staff_role":null,"staff_enabled":null,"staff_hidden":null},"rank":11},{"players":2,"id":"50249","platform":"xb1","main_video":"https:\/\/www.twitch.tv\/videos\/590649584","video_id":"590649584","video_type":"twitch","unit":"Round","format":null,"note":null,"added":"13th, April 2020","other_links":null,"achieved":"17","player1":{"id":"918145","name":"nerd284","flag":"usa","cheater":"0","banned":"0","url":"\/players\/bmVyZDI4NA\/","staff_role":null,"staff_enabled":null,"staff_hidden":null},"player2":{"id":"918146","name":"Pp goat","flag":"usa","cheater":"0","banned":"0","url":"\/players\/UHAgZ29hdA\/","staff_role":null,"staff_enabled":null,"staff_hidden":null}}],"12":[{"players":2,"id":"26695","platform":"ps4","main_video":"https:\/\/youtu.be\/GUCVNFjZS7k","video_id":"GUCVNFjZS7k","video_type":"youtube","unit":"Round","format":null,"note":null,"added":"19th, June 2018","other_links":null,"achieved":"16","player1":{"id":"13442","name":"Freakdog-_-","flag":"england","cheater":"0","banned":"0","url":"\/players\/RnJlYWtkb2ctXy0\/","staff_role":null,"staff_enabled":null,"staff_hidden":null},"player2":{"id":"13458","name":"JoeW0704","flag":"england","cheater":"0","banned":"0","url":"\/players\/Sm9lVzA3MDQ\/","staff_role":null,"staff_enabled":null,"staff_hidden":null},"rank":12},{"players":2,"id":"27797","platform":"xb1","main_video":"https:\/\/www.youtube.com\/watch?v=oLwfhEYH5Ik&feature=youtu.be","video_id":"oLwfhEYH5Ik","video_type":"youtube","unit":"Round","format":null,"note":null,"added":"1st, August 2018","other_links":null,"achieved":"16","player1":{"id":"9243","name":"NerdMan756","flag":"usa","cheater":"0","banned":"0","url":"\/players\/TmVyZE1hbjc1Ng\/","staff_role":null,"staff_enabled":null,"staff_hidden":null},"player2":{"id":"9244","name":"Salty Havoc","flag":"usa","cheater":"0","banned":"0","url":"\/players\/U2FsdHkgSGF2b2M\/","staff_role":null,"staff_enabled":null,"staff_hidden":null}},{"players":2,"id":"29156","platform":"ps4","main_video":"https:\/\/www.youtube.com\/watch?v=mxr4Y9wReNw","video_id":"mxr4Y9wReNw","video_type":"youtube","unit":"Round","format":null,"note":null,"added":"22nd, September 2018","other_links":null,"achieved":"16","player1":{"id":"14235","name":"sebastian4372","flag":"germany","cheater":"0","banned":"0","url":"\/players\/c2ViYXN0aWFuNDM3Mg\/","staff_role":null,"staff_enabled":null,"staff_hidden":null},"player2":{"id":"14234","name":"uN_SnipzZ","flag":"germany","cheater":"0","banned":"0","url":"\/players\/dU5fU25pcHpa\/","staff_role":null,"staff_enabled":null,"staff_hidden":null}}],"13":[{"players":2,"id":"27693","platform":"ps4","main_video":"https:\/\/youtu.be\/oQtOQcEn0dg","video_id":"oQtOQcEn0dg","video_type":"youtube","unit":"Round","format":null,"note":null,"added":"29th, July 2018","other_links":null,"achieved":"14","player1":{"id":"13696","name":"IxI_Cinder_IxI","flag":"usa","cheater":"0","banned":"0","url":"\/players\/SXhJX0NpbmRlcl9JeEk\/","staff_role":null,"staff_enabled":null,"staff_hidden":null},"player2":{"id":"13834","name":"ice_for_life63","flag":"usa","cheater":"0","banned":"0","url":"\/players\/aWNlX2Zvcl9saWZlNjM\/","staff_role":null,"staff_enabled":null,"staff_hidden":null},"rank":13},{"players":2,"id":"28003","platform":"xb1","main_video":"https:\/\/www.twitch.tv\/videos\/294526526?collection=ZW_Mb1PNSBXlvA","video_id":"294526526","video_type":"twitch","unit":"Round","format":null,"note":null,"added":"8th, August 2018","other_links":null,"achieved":"14","player1":{"id":"13943","name":"OG Mr Crabs","flag":"usa","cheater":"0","banned":"0","url":"\/players\/T0cgTXIgQ3JhYnM\/","staff_role":null,"staff_enabled":null,"staff_hidden":null},"player2":{"id":"13944","name":"XDarkshark8X","flag":"usa","cheater":"0","banned":"0","url":"\/players\/WERhcmtzaGFyazhY\/","staff_role":null,"staff_enabled":null,"staff_hidden":null}},{"players":2,"id":"70217","platform":"xb1","main_video":"https:\/\/www.youtube.com\/watch?v=Kr3JolWW2Jk","video_id":"Kr3JolWW2Jk","video_type":"youtube","unit":"Round","format":null,"note":null,"added":"11th, May 2021","other_links":null,"achieved":"14","player1":{"id":"20581","name":"Yolo Knifer 24","flag":"canada","cheater":"0","banned":"0","url":"\/players\/WW9sbyBLbmlmZXIgMjQ\/","staff_role":"Administrator","staff_enabled":"0","staff_hidden":"0"},"player2":{"id":"926032","name":"Sacred","flag":"canada","cheater":"0","banned":"0","url":"\/players\/U2FjcmVk\/","staff_role":null,"staff_enabled":null,"staff_hidden":null}}],"14":[{"players":2,"id":"26600","platform":"ps4","main_video":"https:\/\/youtu.be\/pWvvurgXltM","video_id":"pWvvurgXltM","video_type":"youtube","unit":"Round","format":null,"note":null,"added":"16th, June 2018","other_links":null,"achieved":"13","player1":{"id":"9390","name":"DropRateZ","flag":"canada","cheater":"0","banned":"0","url":"\/players\/RHJvcFJhdGVa\/","staff_role":null,"staff_enabled":null,"staff_hidden":null},"player2":{"id":"13429","name":"Goldtree65","flag":"canada","cheater":"0","banned":"0","url":"\/players\/R29sZHRyZWU2NQ\/","staff_role":null,"staff_enabled":null,"staff_hidden":null},"rank":14},{"players":2,"id":"26730","platform":"xb1","main_video":"https:\/\/www.twitch.tv\/videos\/275764393","video_id":"275764393","video_type":"twitch","unit":"Round","format":null,"note":null,"added":"21st, June 2018","other_links":null,"achieved":"13","player1":{"id":"13369","name":"AlliedGame","flag":"usa","cheater":"0","banned":"0","url":"\/players\/QWxsaWVkR2FtZQ\/","staff_role":null,"staff_enabled":null,"staff_hidden":null},"player2":{"id":"13472","name":"UberJake7","flag":"usa","cheater":"0","banned":"0","url":"\/players\/VWJlckpha2U3\/","staff_role":null,"staff_enabled":null,"staff_hidden":null}},{"players":2,"id":"27493","platform":"ps4","main_video":"https:\/\/www.youtube.com\/watch?v=i6wcFj62S5k","video_id":"i6wcFj62S5k","video_type":"youtube","unit":"Round","format":null,"note":null,"added":"21st, July 2018","other_links":["https:\/\/www.youtube.com\/watch?v=WZokS7wDiV0"],"achieved":"13","player1":{"id":"13757","name":"KT_Zapid","flag":"ar","cheater":"0","banned":"0","url":"\/players\/S1RfWmFwaWQ\/","staff_role":null,"staff_enabled":null,"staff_hidden":null},"player2":{"id":"13758","name":"KT_CitripHD","flag":"ar","cheater":"0","banned":"0","url":"\/players\/S1RfQ2l0cmlwSEQ\/","staff_role":null,"staff_enabled":null,"staff_hidden":null}}],"15":[{"players":2,"id":"26648","platform":"xb1","main_video":"https:\/\/www.twitch.tv\/videos\/274295144","video_id":"274295144","video_type":"twitch","unit":"Round","format":null,"note":null,"added":"17th, June 2018","other_links":null,"achieved":"11","player1":{"id":"13439","name":"FroZen ShotzZz","flag":"usa","cheater":"0","banned":"0","url":"\/players\/RnJvWmVuIFNob3R6Wno\/","staff_role":null,"staff_enabled":null,"staff_hidden":null},"player2":{"id":"13440","name":"TOMCAT 7K","flag":"usa","cheater":"0","banned":"0","url":"\/players\/VE9NQ0FUIDdL\/","staff_role":null,"staff_enabled":null,"staff_hidden":null},"rank":15}]}