{"1":[{"players":4,"id":"87897","platform":"ps4","main_video":"https:\/\/youtu.be\/PlUQ65mnizY","video_id":"PlUQ65mnizY","video_type":"youtube","unit":"Round","format":null,"note":null,"added":"16th, April 2022","other_links":null,"achieved":"51","player1":{"id":"1546168","name":"Ronin411","flag":"usa","cheater":"0","banned":"0","url":"\/players\/Um9uaW40MTE\/","staff_role":null,"staff_enabled":null,"staff_hidden":null},"player2":{"id":"1546169","name":"Grandmaster_XD","flag":"usa","cheater":"0","banned":"0","url":"\/players\/R3JhbmRtYXN0ZXJfWEQ\/","staff_role":null,"staff_enabled":null,"staff_hidden":null},"player3":{"id":"922729","name":"tin_tinjim69","flag":"australia","cheater":"0","banned":"0","url":"\/players\/dGluX3RpbmppbTY5\/","staff_role":null,"staff_enabled":null,"staff_hidden":null},"player4":{"id":"922898","name":"do_something_man","flag":"australia","cheater":"0","banned":"0","url":"\/players\/ZG9fc29tZXRoaW5nX21hbg\/","staff_role":null,"staff_enabled":null,"staff_hidden":null},"rank":1}],"2":[{"players":4,"id":"51487","platform":"ps4","main_video":"https:\/\/www.twitch.tv\/videos\/600912541","video_id":"600912541","video_type":"twitch","unit":"Round","format":null,"note":null,"added":"24th, April 2020","other_links":null,"achieved":"45","player1":{"id":"918691","name":"KillShotGG","flag":"usa","cheater":"0","banned":"0","url":"\/players\/S2lsbFNob3RHRw\/","staff_role":null,"staff_enabled":null,"staff_hidden":null},"player2":{"id":"918692","name":"QuickReviveFTW","flag":"usa","cheater":"0","banned":"0","url":"\/players\/UXVpY2tSZXZpdmVGVFc\/","staff_role":null,"staff_enabled":null,"staff_hidden":null},"player3":{"id":"918694","name":"TexasMade-Cj","flag":"usa","cheater":"0","banned":"0","url":"\/players\/VGV4YXNNYWRlLUNq\/","staff_role":null,"staff_enabled":null,"staff_hidden":null},"player4":{"id":"918756","name":"Dino","flag":"usa","cheater":"0","banned":"0","url":"\/players\/RGlubw\/","staff_role":null,"staff_enabled":null,"staff_hidden":null},"rank":2}],"3":[{"players":4,"id":"49788","platform":"ps4","main_video":"https:\/\/www.twitch.tv\/videos\/585468466","video_id":"585468466","video_type":"twitch","unit":"Round","format":null,"note":null,"added":"7th, April 2020","other_links":null,"achieved":"42","player1":{"id":"13819","name":"TripleJD","flag":"england","cheater":"0","banned":"0","url":"\/players\/VHJpcGxlSkQ\/","staff_role":null,"staff_enabled":null,"staff_hidden":null},"player2":{"id":"13820","name":"G-I-N-G-E-5-0-0","flag":"england","cheater":"0","banned":"0","url":"\/players\/Ry1JLU4tRy1FLTUtMC0w\/","staff_role":null,"staff_enabled":null,"staff_hidden":null},"player3":{"id":"21300","name":"CrazyJaxster","flag":"england","cheater":"0","banned":"0","url":"\/players\/Q3JhenlKYXhzdGVy\/","staff_role":null,"staff_enabled":null,"staff_hidden":null},"player4":{"id":"21299","name":"Its_Only_Jok3R","flag":"england","cheater":"0","banned":"0","url":"\/players\/SXRzX09ubHlfSm9rM1I\/","staff_role":null,"staff_enabled":null,"staff_hidden":null},"rank":3}],"4":[{"players":4,"id":"47524","platform":"ps4","main_video":"https:\/\/youtu.be\/CiqtA3WYlCQ","video_id":"CiqtA3WYlCQ","video_type":"youtube","unit":"Round","format":null,"note":null,"added":"5th, March 2020","other_links":null,"achieved":"38","player1":{"id":"4439","name":"GravityDrop","flag":"usa","cheater":"0","banned":"0","url":"\/players\/R3Jhdml0eURyb3A\/","staff_role":null,"staff_enabled":null,"staff_hidden":null},"player2":{"id":"20942","name":"Thegosys454","flag":"usa","cheater":"0","banned":"0","url":"\/players\/VGhlZ29zeXM0NTQ\/","staff_role":null,"staff_enabled":null,"staff_hidden":null},"player3":{"id":"20943","name":"Skdog3","flag":"usa","cheater":"0","banned":"0","url":"\/players\/U2tkb2cz\/","staff_role":null,"staff_enabled":null,"staff_hidden":null},"player4":{"id":"20944","name":"Big_chief_2003","flag":"usa","cheater":"0","banned":"0","url":"\/players\/QmlnX2NoaWVmXzIwMDM\/","staff_role":null,"staff_enabled":null,"staff_hidden":null},"rank":4}],"5":[{"players":4,"id":"41447","platform":"ps4","main_video":"https:\/\/youtu.be\/XMI7Ktx79sQ","video_id":"XMI7Ktx79sQ","video_type":"youtube","unit":"Round","format":null,"note":null,"added":"13th, October 2019","other_links":null,"achieved":"32","player1":{"id":"9857","name":"rian-_-mc14","flag":"scotland","cheater":"0","banned":"0","url":"\/players\/cmlhbi1fLW1jMTQ\/","staff_role":null,"staff_enabled":null,"staff_hidden":null},"player2":{"id":"19285","name":"Ghost-Blxon","flag":"germany","cheater":"0","banned":"0","url":"\/players\/R2hvc3QtQmx4b24\/","staff_role":null,"staff_enabled":null,"staff_hidden":null},"player3":{"id":"8409","name":"A101Pro1","flag":"england","cheater":"0","banned":"0","url":"\/players\/QTEwMVBybzE\/","staff_role":null,"staff_enabled":null,"staff_hidden":null},"player4":{"id":"19309","name":"Fleischhaken81","flag":"germany","cheater":"0","banned":"0","url":"\/players\/RmxlaXNjaGhha2VuODE\/","staff_role":null,"staff_enabled":null,"staff_hidden":null},"rank":5}],"6":[{"players":4,"id":"40216","platform":"pc","main_video":"https:\/\/www.twitch.tv\/videos\/483780370","video_id":"483780370","video_type":"twitch","unit":"Round","format":null,"note":null,"added":"20th, September 2019","other_links":null,"achieved":"11","player1":{"id":"14149","name":"Halo","flag":"usa","cheater":"0","banned":"0","url":"\/players\/SGFsbw\/","staff_role":null,"staff_enabled":null,"staff_hidden":null},"player2":{"id":"14145","name":"OwlEyes","flag":"usa","cheater":"0","banned":"0","url":"\/players\/T3dsRXllcw\/","staff_role":null,"staff_enabled":null,"staff_hidden":null},"player3":{"id":"18862","name":"Balo","flag":"israel","cheater":"0","banned":"0","url":"\/players\/QmFsbw\/","staff_role":null,"staff_enabled":null,"staff_hidden":null},"player4":{"id":"18865","name":"Kumquat","flag":"israel","cheater":"0","banned":"0","url":"\/players\/S3VtcXVhdA\/","staff_role":null,"staff_enabled":null,"staff_hidden":null},"rank":6}]}