{"1":[{"players":1,"id":"12866","platform":"ps4","main_video":"https:\/\/www.youtube.com\/watch?v=TkJKrrIJhgg","video_id":"TkJKrrIJhgg","video_type":"youtube","unit":"Round","format":null,"note":null,"added":"29th, November 2018","other_links":null,"achieved":"255","player1":{"id":"6831","name":"mark van leerdam","flag":"netherlands","cheater":"0","banned":"0","url":"\/players\/bWFyayB2YW4gbGVlcmRhbQ\/","staff_role":null,"staff_enabled":null,"staff_hidden":null},"rank":1},{"players":1,"id":"54360","platform":"ps4","main_video":"https:\/\/www.youtube.com\/watch?v=nq-oC8wLVy4","video_id":"nq-oC8wLVy4","video_type":"youtube","unit":"Round","format":null,"note":null,"added":"14th, May 2020","other_links":["https:\/\/www.twitch.tv\/blackscreenon254\/videos?filter=highlights&sort=time"],"achieved":"255","player1":{"id":"4483","name":"kxg124","flag":"usa","cheater":"0","banned":"0","url":"\/players\/a3hnMTI0\/","staff_role":null,"staff_enabled":null,"staff_hidden":null}},{"players":1,"id":"107475","platform":"ps4","main_video":"https:\/\/www.youtube.com\/watch?v=6_2d8BskOYU","video_id":"6_2d8BskOYU","video_type":"youtube","unit":"Round","format":null,"note":null,"added":"16th, August 2023","other_links":null,"achieved":"255","player1":{"id":"924906","name":"InsomniaVirus","flag":"canada","cheater":"0","banned":"0","url":"\/players\/SW5zb21uaWFWaXJ1cw\/","staff_role":null,"staff_enabled":null,"staff_hidden":null}}],"2":[{"players":1,"id":"19708","platform":"ps4","main_video":"https:\/\/youtu.be\/aHA81oJ62CU","video_id":"aHA81oJ62CU","video_type":"youtube","unit":"Round","format":null,"note":null,"added":"13th, June 2018","other_links":["https:\/\/youtu.be\/K-ACUn2_ugw","https:\/\/www.twitch.tv\/videos\/267090837","https:\/\/www.twitch.tv\/videos\/267092301","https:\/\/www.twitch.tv\/videos\/267093472","https:\/\/www.twitch.tv\/videos\/270589193","https:\/\/www.twitch.tv\/videos\/270592309","https:\/\/www.twitch.tv\/videos\/270593358","https:\/\/www.twitch.tv\/videos\/270594858","https:\/\/www.twitch.tv\/videos\/271419470","https:\/\/www.twitch.tv\/videos\/271419813","https:\/\/www.twitch.tv\/videos\/271420372","https:\/\/www.twitch.tv\/videos\/271420980","https:\/\/youtu.be\/MlKu5iO4GqA","https:\/\/youtu.be\/nSj7wmpfnLI","https:\/\/youtu.be\/incNDU4UknM","https:\/\/youtu.be\/tOyuQQien3E","https:\/\/youtu.be\/Cjhq_-I9XLo","https:\/\/www.twitch.tv\/videos\/270570520","https:\/\/www.twitch.tv\/videos\/270678905","https:\/\/www.twitch.tv\/videos\/270856620","https:\/\/www.twitch.tv\/videos\/271421860","https:\/\/www.twitch.tv\/videos\/271423076","https:\/\/www.twitch.tv\/videos\/271423558","https:\/\/www.twitch.tv\/videos\/271423838"],"achieved":"232","player1":{"id":"5736","name":"Desantis101","flag":"usa","cheater":"0","banned":"0","url":"\/players\/RGVzYW50aXMxMDE\/","staff_role":null,"staff_enabled":null,"staff_hidden":null},"rank":2}],"3":[{"players":1,"id":"107578","platform":"pc","main_video":"https:\/\/www.twitch.tv\/videos\/1858807323","video_id":"1858807323","video_type":"twitch","unit":"Round","format":null,"note":null,"added":"29th, June 2023","other_links":["https:\/\/www.twitch.tv\/videos\/1858756018","https:\/\/www.twitch.tv\/videos\/1858757172","https:\/\/www.twitch.tv\/videos\/1858757677","https:\/\/www.twitch.tv\/videos\/1858757973","https:\/\/www.twitch.tv\/videos\/1858758760"],"achieved":"223","player1":{"id":"2720","name":"JxstTacTicaL","flag":"germany","cheater":"0","banned":"0","url":"\/players\/SnhzdFRhY1RpY2FM\/","staff_role":null,"staff_enabled":null,"staff_hidden":null},"rank":3}],"4":[{"players":1,"id":"17721","platform":"ps4","main_video":"https:\/\/www.youtube.com\/watch?v=ND7k5ccV6pI","video_id":"ND7k5ccV6pI","video_type":"youtube","unit":"Round","format":null,"note":null,"added":"7th, August 2017","other_links":["https:\/\/www.twitch.tv\/darksidders\/manager\/highlights","https:\/\/www.youtube.com\/channel\/UCxZeItbrqnhAvFaUCPQZkIw\/videos"],"achieved":"197","player1":{"id":"6916","name":"GZTK DarkSidders","flag":"france","cheater":"0","banned":"0","url":"\/players\/R1pUSyBEYXJrU2lkZGVycw\/","staff_role":null,"staff_enabled":null,"staff_hidden":null},"rank":4}],"5":[{"players":1,"id":"16527","platform":"ps4","main_video":"https:\/\/www.youtube.com\/watch?v=7ON1iIZWjes","video_id":"7ON1iIZWjes","video_type":"youtube","unit":"Round","format":null,"note":null,"added":"7th, July 2017","other_links":["https:\/\/youtu.be\/1n-W_dw05K4","https:\/\/youtu.be\/oAYlfMBZP0A"," https:\/\/youtu.be\/TAtSTwWGByA","https:\/\/youtu.be\/W91ujSYtO5U","https:\/\/youtu.be\/W91ujSYtO5U","https:\/\/youtu.be\/oATEpOiI53M","https:\/\/youtu.be\/yIXywPw4VN4","https:\/\/youtu.be\/KF99PhxpDvQ","https:\/\/youtu.be\/gAi4PMYbyJA","https:\/\/youtu.be\/8DtlS4iTOVA","https:\/\/youtu.be\/Avs8bYHXk5o","https:\/\/youtu.be\/x5aaNo9G7fE"],"achieved":"183","player1":{"id":"1098","name":"in2itScott","flag":"usa","cheater":"0","banned":"0","url":"\/players\/aW4yaXRTY290dA\/","staff_role":null,"staff_enabled":null,"staff_hidden":null},"rank":5},{"players":1,"id":"19322","platform":"ps4","main_video":"https:\/\/youtu.be\/Pn0T41cF0C4","video_id":"Pn0T41cF0C4","video_type":"youtube","unit":"Round","format":null,"note":null,"added":"11th, August 2017","other_links":null,"achieved":"183","player1":{"id":"10582","name":"mrblondesghost","flag":"usa","cheater":"0","banned":"0","url":"\/players\/bXJibG9uZGVzZ2hvc3Q\/","staff_role":null,"staff_enabled":null,"staff_hidden":null}}],"6":[{"players":1,"id":"106701","platform":"pc","main_video":"https:\/\/www.youtube.com\/watch?v=OrHaVnxDCJE","video_id":"OrHaVnxDCJE","video_type":"youtube","unit":"Round","format":null,"note":null,"added":"8th, June 2023","other_links":["https:\/\/www.youtube.com\/playlist?list=PLCarQI8WPOf9qKTfJWdyULSuf2nU_WzWA"],"achieved":"181","player1":{"id":"1544463","name":"TailsCanFly","flag":"usa","cheater":"0","banned":"0","url":"\/players\/VGFpbHNDYW5GbHk\/","staff_role":null,"staff_enabled":null,"staff_hidden":null},"rank":6}],"7":[{"players":1,"id":"75910","platform":"pc","main_video":"https:\/\/www.twitch.tv\/videos\/1119500173","video_id":"1119500173","video_type":"twitch","unit":"Round","format":null,"note":null,"added":"16th, August 2021","other_links":["https:\/\/youtu.be\/VEIEBCJpcmg","https:\/\/www.twitch.tv\/videos\/1119494638","https:\/\/www.twitch.tv\/videos\/1119495642","https:\/\/www.twitch.tv\/videos\/1119496475","https:\/\/www.twitch.tv\/videos\/1119497541","https:\/\/www.twitch.tv\/videos\/1119499464"],"achieved":"176","player1":{"id":"918965","name":"NicZombies","flag":"usa","cheater":"0","banned":"0","url":"\/players\/TmljWm9tYmllcw\/","staff_role":null,"staff_enabled":null,"staff_hidden":null},"rank":7}],"8":[{"players":1,"id":"12632","platform":"ps4","main_video":"https:\/\/www.twitch.tv\/videos\/151245624","video_id":"151245624","video_type":"twitch","unit":"Round","format":null,"note":null,"added":"15th, June 2017","other_links":["https:\/\/www.twitch.tv\/videos\/150757663","https:\/\/www.twitch.tv\/videos\/150757290","https:\/\/www.twitch.tv\/videos\/150524958","https:\/\/www.twitch.tv\/videos\/150293834","https:\/\/www.twitch.tv\/videos\/150293545","https:\/\/www.twitch.tv\/videos\/150293265","https:\/\/www.twitch.tv\/videos\/150292950","https:\/\/www.twitch.tv\/videos\/150292682","https:\/\/www.twitch.tv\/videos\/150292438"],"achieved":"164","player1":{"id":"1547","name":"Hampton","flag":"usa","cheater":"0","banned":"0","url":"\/players\/SGFtcHRvbg\/","staff_role":null,"staff_enabled":null,"staff_hidden":null},"rank":8}],"9":[{"players":1,"id":"91212","platform":"pc","main_video":"https:\/\/www.twitch.tv\/videos\/1503960098","video_id":"1503960098","video_type":"twitch","unit":"Round","format":null,"note":null,"added":"15th, June 2022","other_links":["https:\/\/www.twitch.tv\/collections\/mMaM67mx9xaKHg"],"achieved":"152","player1":{"id":"1548124","name":"Byburthe","flag":"canada","cheater":"0","banned":"0","url":"\/players\/QnlidXJ0aGU\/","staff_role":null,"staff_enabled":null,"staff_hidden":null},"rank":9}],"10":[{"players":1,"id":"39105","platform":"pc","main_video":"https:\/\/www.youtube.com\/watch?v=NxHnbbVP9bU","video_id":"NxHnbbVP9bU","video_type":"youtube","unit":"Round","format":null,"note":null,"added":"24th, August 2019","other_links":null,"achieved":"151","player1":{"id":"19054","name":"Zi0","flag":"poland","cheater":"0","banned":"0","url":"\/players\/Wmkw\/","staff_role":null,"staff_enabled":null,"staff_hidden":null},"rank":10}],"11":[{"players":1,"id":"32404","platform":"ps4","main_video":"https:\/\/www.youtube.com\/watch?v=O-d0r53doVs","video_id":"O-d0r53doVs","video_type":"youtube","unit":"Round","format":null,"note":null,"added":"17th, December 2018","other_links":null,"achieved":"150","player1":{"id":"91","name":"MUSLOO","flag":"spain","cheater":"0","banned":"0","url":"\/players\/TVVTTE9P\/","staff_role":null,"staff_enabled":null,"staff_hidden":null},"rank":11}],"12":[{"players":1,"id":"102599","platform":"ps4","main_video":"https:\/\/youtu.be\/oocDU13zVSI","video_id":"oocDU13zVSI","video_type":"youtube","unit":"Round","format":null,"note":null,"added":"19th, March 2023","other_links":null,"achieved":"143","player1":{"id":"1549313","name":"Harlekin Zombie","flag":"germany","cheater":"0","banned":"0","url":"\/players\/SGFybGVraW4gWm9tYmll\/","staff_role":null,"staff_enabled":null,"staff_hidden":null},"rank":12}],"13":[{"players":1,"id":"32397","platform":"ps4","main_video":"https:\/\/youtu.be\/OZlloGQhkSQ","video_id":"OZlloGQhkSQ","video_type":"youtube","unit":"Round","format":null,"note":null,"added":"16th, December 2018","other_links":null,"achieved":"140","player1":{"id":"21","name":"IlSteveIl","flag":"england","cheater":"0","banned":"0","url":"\/players\/SWxTdGV2ZUls\/","staff_role":null,"staff_enabled":null,"staff_hidden":null},"rank":13}],"14":[{"players":1,"id":"31465","platform":"ps4","main_video":"https:\/\/youtu.be\/rrMLexWbeOw","video_id":"rrMLexWbeOw","video_type":"youtube","unit":"Round","format":null,"note":null,"added":"16th, November 2018","other_links":["https:\/\/youtu.be\/rrMLexWbeOw","https:\/\/youtu.be\/M84HnbN7y9k","https:\/\/youtu.be\/_3CvP8hwmKs","https:\/\/youtu.be\/B7ntl4Xy2S8"],"achieved":"121","player1":{"id":"13640","name":"A7mad_721","flag":"kuwait","cheater":"0","banned":"0","url":"\/players\/QTdtYWRfNzIx\/","staff_role":null,"staff_enabled":null,"staff_hidden":null},"rank":14},{"players":1,"id":"101773","platform":"ps4","main_video":"https:\/\/youtu.be\/S47lKCLY8S8","video_id":"S47lKCLY8S8","video_type":"youtube","unit":"Round","format":null,"note":null,"added":"10th, March 2023","other_links":["https:\/\/youtu.be\/exXbP3I6t7M","https:\/\/youtu.be\/locYLr-mJek","https:\/\/youtu.be\/5s0ElRljG5w","https:\/\/youtu.be\/F41elUtmc80","https:\/\/youtu.be\/P1fqGMwIibA","https:\/\/youtu.be\/r7xoVuPuX_s","https:\/\/www.twitch.tv\/zbrazilianzombie\/v\/1755302029?sr=a&t=0s"],"achieved":"121","player1":{"id":"1550334","name":"BrazilianZombie","flag":"brazil","cheater":"0","banned":"0","url":"\/players\/QnJhemlsaWFuWm9tYmll\/","staff_role":null,"staff_enabled":null,"staff_hidden":null}}],"15":[{"players":1,"id":"31724","platform":"ps4","main_video":"https:\/\/youtu.be\/yz4Rzimtuo0","video_id":"yz4Rzimtuo0","video_type":"youtube","unit":"Round","format":null,"note":null,"added":"24th, November 2018","other_links":null,"achieved":"120","player1":{"id":"4556","name":"Jordi Pi","flag":"spain","cheater":"0","banned":"0","url":"\/players\/Sm9yZGkgUGk\/","staff_role":null,"staff_enabled":null,"staff_hidden":null},"rank":15}],"16":[{"players":1,"id":"20457","platform":"ps4","main_video":"https:\/\/youtu.be\/lpTNE62ZKDw","video_id":"lpTNE62ZKDw","video_type":"youtube","unit":"Round","format":null,"note":null,"added":"28th, August 2017","other_links":null,"achieved":"114","player1":{"id":"11187","name":"Or1171","flag":"israel","cheater":"0","banned":"0","url":"\/players\/T3IxMTcx\/","staff_role":null,"staff_enabled":null,"staff_hidden":null},"rank":16}],"17":[{"players":1,"id":"21835","platform":"ps4","main_video":"https:\/\/www.twitch.tv\/videos\/157075474","video_id":"157075474","video_type":"twitch","unit":"Round","format":null,"note":null,"added":"22nd, September 2017","other_links":["https:\/\/www.twitch.tv\/videos\/157030862","https:\/\/www.twitch.tv\/videos\/156752475"],"achieved":"106","player1":{"id":"4785","name":"SyntexZombies","flag":"germany","cheater":"0","banned":"0","url":"\/players\/U3ludGV4Wm9tYmllcw\/","staff_role":null,"staff_enabled":null,"staff_hidden":null},"rank":17}],"18":[{"players":1,"id":"24876","platform":"ps4","main_video":"https:\/\/www.twitch.tv\/videos\/253126928","video_id":"253126928","video_type":"twitch","unit":"Round","format":null,"note":null,"added":"23rd, April 2018","other_links":null,"achieved":"105","player1":{"id":"12804","name":"Chinodeone","flag":"usa","cheater":"0","banned":"0","url":"\/players\/Q2hpbm9kZW9uZQ\/","staff_role":null,"staff_enabled":null,"staff_hidden":null},"rank":18}],"19":[{"players":1,"id":"25354","platform":"ps4","main_video":"https:\/\/www.youtube.com\/watch?v=6etupBcURY4","video_id":"6etupBcURY4","video_type":"youtube","unit":"Round","format":null,"note":null,"added":"9th, April 2018","other_links":["https:\/\/www.youtube.com\/watch?v=yWbdhUA_aaI","https:\/\/www.youtube.com\/watch?v=qCg0psixlDs","https:\/\/www.youtube.com\/watch?v=bo4SwE4SM1A","https:\/\/www.youtube.com\/watch?v=8VqdVxYHgfM"],"achieved":"102","player1":{"id":"919838","name":"CallMeWebbie","flag":"usa","cheater":"0","banned":"0","url":"\/players\/Q2FsbE1lV2ViYmll\/","staff_role":null,"staff_enabled":null,"staff_hidden":null},"rank":19}],"20":[{"players":1,"id":"23963","platform":"ps4","main_video":"https:\/\/www.twitch.tv\/videos\/231624401","video_id":"231624401","video_type":"twitch","unit":"Round","format":null,"note":null,"added":"25th, February 2018","other_links":["https:\/\/www.twitch.tv\/videos\/231624401"],"achieved":"101","player1":{"id":"12443","name":"iRuLeZz-_GaLaxXy","flag":"ar","cheater":"0","banned":"0","url":"\/players\/aVJ1TGVaei1fR2FMYXhYeQ\/","staff_role":null,"staff_enabled":null,"staff_hidden":null},"rank":20}],"21":[{"players":1,"id":"55606","platform":"ps4","main_video":"https:\/\/www.twitch.tv\/videos\/625540073","video_id":"625540073","video_type":"twitch","unit":"Round","format":null,"note":null,"added":"24th, May 2020","other_links":null,"achieved":"100","player1":{"id":"920431","name":"RealFoot","flag":"spain","cheater":"0","banned":"0","url":"\/players\/UmVhbEZvb3Q\/","staff_role":null,"staff_enabled":null,"staff_hidden":null},"rank":21}],"22":[{"players":1,"id":"26759","platform":"ps4","main_video":"https:\/\/www.twitch.tv\/videos\/276370619","video_id":"276370619","video_type":"twitch","unit":"Round","format":null,"note":null,"added":"22nd, June 2018","other_links":null,"achieved":"94","player1":{"id":"13492","name":"SirEliaas","flag":"ar","cheater":"0","banned":"0","url":"\/players\/U2lyRWxpYWFz\/","staff_role":null,"staff_enabled":null,"staff_hidden":null},"rank":22}],"23":[{"players":1,"id":"17433","platform":"xb1","main_video":"https:\/\/www.twitch.tv\/videos\/159949613?t=","video_id":"159949613","video_type":"twitch","unit":"Round","format":null,"note":null,"added":"18th, July 2017","other_links":["https:\/\/www.twitch.tv\/videos\/159949613?t="],"achieved":"89","player1":{"id":"9459","name":"Nazzify","flag":"usa","cheater":"0","banned":"0","url":"\/players\/TmF6emlmeQ\/","staff_role":null,"staff_enabled":null,"staff_hidden":null},"rank":23}],"24":[{"players":1,"id":"109108","platform":"pc","main_video":"https:\/\/www.youtube.com\/watch?v=mY3SEcjaxks","video_id":"mY3SEcjaxks","video_type":"youtube","unit":"Round","format":null,"note":null,"added":"29th, July 2023","other_links":null,"achieved":"88","player1":{"id":"1553156","name":"korrdn","flag":"australia","cheater":"0","banned":"0","url":"\/players\/a29ycmRu\/","staff_role":null,"staff_enabled":null,"staff_hidden":null},"rank":24}],"25":[{"players":1,"id":"19181","platform":"ps4","main_video":"https:\/\/www.youtube.com\/watch?v=ilQiDHrg3TE","video_id":"ilQiDHrg3TE","video_type":"youtube","unit":"Round","format":null,"note":null,"added":"10th, August 2017","other_links":null,"achieved":"84","player1":{"id":"10521","name":"XxStormXx208","flag":"usa","cheater":"0","banned":"0","url":"\/players\/WHhTdG9ybVh4MjA4\/","staff_role":null,"staff_enabled":null,"staff_hidden":null},"rank":25}],"26":[{"players":1,"id":"27824","platform":"ps4","main_video":"https:\/\/www.youtube.com\/watch?v=fZTKtexGgjU","video_id":"fZTKtexGgjU","video_type":"youtube","unit":"Round","format":null,"note":null,"added":"2nd, August 2018","other_links":null,"achieved":"78","player1":{"id":"13879","name":"Paraxxdise","flag":"usa","cheater":"0","banned":"0","url":"\/players\/UGFyYXh4ZGlzZQ\/","staff_role":null,"staff_enabled":null,"staff_hidden":null},"rank":26}]}