{"1":[{"players":1,"id":"94897","platform":"pc","main_video":"https:\/\/www.twitch.tv\/videos\/1571926921","video_id":"1571926921","video_type":"twitch","unit":"Round","format":null,"note":null,"added":"25th, August 2022","other_links":null,"achieved":"50","player1":{"id":"16245","name":"Wazbags","flag":"trinidad","cheater":"0","banned":"0","url":"\/players\/V2F6YmFncw\/","staff_role":null,"staff_enabled":null,"staff_hidden":null},"rank":1}],"2":[{"players":1,"id":"10050","platform":"ps4","main_video":"https:\/\/www.twitch.tv\/videos\/145019877","video_id":"145019877","video_type":"twitch","unit":"Round","format":null,"note":null,"added":"19th, May 2017","other_links":null,"achieved":"42","player1":{"id":"4306","name":"reunionai25","flag":"france","cheater":"0","banned":"0","url":"\/players\/cmV1bmlvbmFpMjU\/","staff_role":null,"staff_enabled":null,"staff_hidden":null},"rank":2},{"players":1,"id":"35018","platform":"ps4","main_video":"https:\/\/youtu.be\/RgcsO7G5Yck","video_id":"RgcsO7G5Yck","video_type":"youtube","unit":"Round","format":null,"note":null,"added":"18th, April 2019","other_links":["https:\/\/youtu.be\/ry9Eo2rtFd0","https:\/\/youtu.be\/BaHiz4QYbWc"],"achieved":"42","player1":{"id":"10626","name":"gianeuphorik17","flag":"italy","cheater":"0","banned":"0","url":"\/players\/Z2lhbmV1cGhvcmlrMTc\/","staff_role":null,"staff_enabled":null,"staff_hidden":null}}],"3":[{"players":1,"id":"87112","platform":"xb1","main_video":"https:\/\/www.youtube.com\/watch?v=CEwH5wjTUi4","video_id":"CEwH5wjTUi4","video_type":"youtube","unit":"Round","format":null,"note":null,"added":"8th, April 2022","other_links":["https:\/\/www.youtube.com\/watch?v=uT8O5PYuMU8","https:\/\/www.youtube.com\/watch?v=Xcggyhe8KWM"],"achieved":"41","player1":{"id":"923492","name":"theone53","flag":"england","cheater":"0","banned":"0","url":"\/players\/dGhlb25lNTM\/","staff_role":null,"staff_enabled":null,"staff_hidden":null},"rank":3}],"4":[{"players":1,"id":"8665","platform":"ps4","main_video":"https:\/\/www.twitch.tv\/videos\/118996672","video_id":"118996672","video_type":"twitch","unit":"Round","format":null,"note":null,"added":"1st, February 2017","other_links":null,"achieved":"28","player1":{"id":"2434","name":"Anton_the_one","flag":"slovenia","cheater":"0","banned":"0","url":"\/players\/QW50b25fdGhlX29uZQ\/","staff_role":null,"staff_enabled":null,"staff_hidden":null},"rank":4}],"5":[{"players":1,"id":"22511","platform":"ps4","main_video":"https:\/\/youtu.be\/0lD8WE76tug","video_id":"0lD8WE76tug","video_type":"youtube","unit":"Round","format":null,"note":null,"added":"13th, October 2017","other_links":null,"achieved":"27","player1":{"id":"10126","name":"MoatazHd","flag":"usa","cheater":"0","banned":"0","url":"\/players\/TW9hdGF6SGQ\/","staff_role":null,"staff_enabled":null,"staff_hidden":null},"rank":5}],"6":[{"players":1,"id":"104604","platform":"pc","main_video":"https:\/\/www.twitch.tv\/videos\/1804497688","video_id":"1804497688","video_type":"twitch","unit":"Round","format":null,"note":null,"added":"26th, April 2023","other_links":null,"achieved":"21","player1":{"id":"1549344","name":"F3rking19","flag":"spain","cheater":"0","banned":"0","url":"\/players\/RjNya2luZzE5\/","staff_role":null,"staff_enabled":null,"staff_hidden":null},"rank":6}],"7":[{"players":1,"id":"6995","platform":"ps4","main_video":"https:\/\/www.twitch.tv\/infinitystella\/v\/96466939","video_id":"96466939","video_type":"twitch","unit":"Round","format":null,"note":null,"added":"22nd, October 2016","other_links":null,"achieved":"20","player1":{"id":"3824","name":"Miss InfinityStella","flag":"france","cheater":"0","banned":"0","url":"\/players\/TWlzcyBJbmZpbml0eVN0ZWxsYQ\/","staff_role":null,"staff_enabled":null,"staff_hidden":null},"rank":7}],"8":[{"players":1,"id":"103752","platform":"ps4","main_video":"https:\/\/www.twitch.tv\/videos\/1789510441?t=0h0m11s","video_id":"1789510441","video_type":"twitch","unit":"Round","format":null,"note":null,"added":"10th, April 2023","other_links":null,"achieved":"19","player1":{"id":"1551589","name":"snipingwolf2500","flag":"england","cheater":"0","banned":"0","url":"\/players\/c25pcGluZ3dvbGYyNTAw\/","staff_role":null,"staff_enabled":null,"staff_hidden":null},"rank":8}],"9":[{"players":1,"id":"8403","platform":"pc","main_video":"https:\/\/www.youtube.com\/watch?v=_2nmy9_TcjU","video_id":"_2nmy9_TcjU","video_type":"youtube","unit":"Round","format":null,"note":null,"added":"14th, January 2017","other_links":null,"achieved":"18","player1":{"id":"1702","name":"BoZ-Masterkill","flag":"france","cheater":"0","banned":"0","url":"\/players\/Qm9aLU1hc3RlcmtpbGw\/","staff_role":null,"staff_enabled":null,"staff_hidden":null},"rank":9},{"players":1,"id":"108646","platform":"ps4","main_video":"https:\/\/youtu.be\/0YbTrdKD3Y4","video_id":"0YbTrdKD3Y4","video_type":"youtube","unit":"Round","format":null,"note":null,"added":"19th, July 2023","other_links":null,"achieved":"18","player1":{"id":"1543860","name":"Jealous Lettuce","flag":"scotland","cheater":"0","banned":"0","url":"\/players\/SmVhbG91cyBMZXR0dWNl\/","staff_role":null,"staff_enabled":null,"staff_hidden":null}}],"10":[{"players":1,"id":"106332","platform":"ps4","main_video":"https:\/\/www.youtube.com\/live\/SqW6SCduxdE?feature=share","video_id":"SqW6SCduxdE","video_type":"youtube","unit":"Round","format":null,"note":null,"added":"13th, June 2023","other_links":null,"achieved":"17","player1":{"id":"1552237","name":"YTxdBlackwood","flag":"usa","cheater":"0","banned":"0","url":"\/players\/WVR4ZEJsYWNrd29vZA\/","staff_role":null,"staff_enabled":null,"staff_hidden":null},"rank":10}],"11":[{"players":1,"id":"7427","platform":"pc","main_video":"https:\/\/www.youtube.com\/watch?v=lBrswNg3kDQ","video_id":"lBrswNg3kDQ","video_type":"youtube","unit":"Round","format":null,"note":null,"added":"14th, November 2016","other_links":null,"achieved":"16","player1":{"id":"4053","name":"EpicGamerNL","flag":"netherlands","cheater":"0","banned":"0","url":"\/players\/RXBpY0dhbWVyTkw\/","staff_role":null,"staff_enabled":null,"staff_hidden":null},"rank":11},{"players":1,"id":"8212","platform":"ps4","main_video":"https:\/\/www.twitch.tv\/gtamafiia\/v\/109331673","video_id":"109331673","video_type":"twitch","unit":"Round","format":null,"note":null,"added":"4th, January 2017","other_links":null,"achieved":"16","player1":{"id":"3032","name":"gtamafiia","flag":"germany","cheater":"0","banned":"0","url":"\/players\/Z3RhbWFmaWlh\/","staff_role":null,"staff_enabled":null,"staff_hidden":null}},{"players":1,"id":"20028","platform":"ps4","main_video":"https:\/\/youtu.be\/GFd0eo542IE","video_id":"GFd0eo542IE","video_type":"youtube","unit":"Round","format":null,"note":null,"added":"22nd, August 2017","other_links":null,"achieved":"16","player1":{"id":"10909","name":"CaHiLlSeR-007","flag":"ireland","cheater":"0","banned":"0","url":"\/players\/Q2FIaUxsU2VSLTAwNw\/","staff_role":null,"staff_enabled":null,"staff_hidden":null}},{"players":1,"id":"39552","platform":"ps4","main_video":"https:\/\/youtu.be\/0erXT2tmT2I","video_id":"0erXT2tmT2I","video_type":"youtube","unit":"Round","format":null,"note":null,"added":"3rd, September 2019","other_links":null,"achieved":"16","player1":{"id":"18794","name":"TobyJB","flag":"england","cheater":"0","banned":"0","url":"\/players\/VG9ieUpC\/","staff_role":null,"staff_enabled":null,"staff_hidden":null}},{"players":1,"id":"43475","platform":"xb1","main_video":"https:\/\/youtu.be\/qXF3xu7XBCY","video_id":"qXF3xu7XBCY","video_type":"youtube","unit":"Round","format":null,"note":null,"added":"9th, December 2019","other_links":null,"achieved":"16","player1":{"id":"19813","name":"pieguyzach","flag":"usa","cheater":"0","banned":"0","url":"\/players\/cGllZ3V5emFjaA\/","staff_role":null,"staff_enabled":null,"staff_hidden":null}},{"players":1,"id":"57721","platform":"xb1","main_video":"https:\/\/www.twitch.tv\/videos\/652082785","video_id":"652082785","video_type":"twitch","unit":"Round","format":null,"note":null,"added":"16th, June 2020","other_links":null,"achieved":"16","player1":{"id":"917915","name":"xtermenator217","flag":"usa","cheater":"0","banned":"0","url":"\/players\/eHRlcm1lbmF0b3IyMTc\/","staff_role":null,"staff_enabled":null,"staff_hidden":null}},{"players":1,"id":"82158","platform":"ps4","main_video":"https:\/\/youtu.be\/RATcXRN4dQ0","video_id":"RATcXRN4dQ0","video_type":"youtube","unit":"Round","format":null,"note":null,"added":"29th, December 2021","other_links":null,"achieved":"16","player1":{"id":"1545293","name":"FrancUchiha","flag":"usa","cheater":"0","banned":"0","url":"\/players\/RnJhbmNVY2hpaGE\/","staff_role":null,"staff_enabled":null,"staff_hidden":null}},{"players":1,"id":"88092","platform":"pc","main_video":"https:\/\/www.twitch.tv\/videos\/1460826344","video_id":"1460826344","video_type":"twitch","unit":"Round","format":null,"note":null,"added":"19th, April 2022","other_links":null,"achieved":"16","player1":{"id":"1547261","name":"Exxotic","flag":"italy","cheater":"0","banned":"0","url":"\/players\/RXh4b3RpYw\/","staff_role":null,"staff_enabled":null,"staff_hidden":null}},{"players":1,"id":"92385","platform":"pc","main_video":"https:\/\/www.youtube.com\/watch?v=sNVxcBA-Qdo","video_id":"sNVxcBA-Qdo","video_type":"youtube","unit":"Round","format":null,"note":null,"added":"11th, July 2022","other_links":null,"achieved":"16","player1":{"id":"1548470","name":"SappoQueen","flag":"england","cheater":"0","banned":"0","url":"\/players\/U2FwcG9RdWVlbg\/","staff_role":null,"staff_enabled":null,"staff_hidden":null}},{"players":1,"id":"106063","platform":"pc","main_video":"https:\/\/youtu.be\/es9e4UjpBNs","video_id":"es9e4UjpBNs","video_type":"youtube","unit":"Round","format":null,"note":null,"added":"27th, May 2023","other_links":null,"achieved":"16","player1":{"id":"1552222","name":"Donete","flag":"spain","cheater":"0","banned":"0","url":"\/players\/RG9uZXRl\/","staff_role":null,"staff_enabled":null,"staff_hidden":null}},{"players":1,"id":"108309","platform":"pc","main_video":"https:\/\/youtu.be\/JK4MhvLEIig","video_id":"JK4MhvLEIig","video_type":"youtube","unit":"Round","format":null,"note":null,"added":"12th, July 2023","other_links":null,"achieved":"16","player1":{"id":"1552844","name":"eruuc","flag":"usa","cheater":"0","banned":"0","url":"\/players\/ZXJ1dWM\/","staff_role":null,"staff_enabled":null,"staff_hidden":null}}],"12":[{"players":1,"id":"9025","platform":"ps4","main_video":"https:\/\/youtu.be\/Mwamo-DdFhE","video_id":"Mwamo-DdFhE","video_type":"youtube","unit":"Round","format":null,"note":null,"added":"16th, February 2017","other_links":null,"achieved":"15","player1":{"id":"4716","name":"LautaroCarp","flag":"ar","cheater":"0","banned":"0","url":"\/players\/TGF1dGFyb0NhcnA\/","staff_role":null,"staff_enabled":null,"staff_hidden":null},"rank":12},{"players":1,"id":"21642","platform":"ps4","main_video":"https:\/\/youtu.be\/I1GOeuEa2jM","video_id":"I1GOeuEa2jM","video_type":"youtube","unit":"Round","format":null,"note":null,"added":"18th, September 2017","other_links":null,"achieved":"15","player1":{"id":"11688","name":"robofett28","flag":"ireland","cheater":"0","banned":"0","url":"\/players\/cm9ib2ZldHQyOA\/","staff_role":null,"staff_enabled":null,"staff_hidden":null}},{"players":1,"id":"45007","platform":"xb1","main_video":"https:\/\/www.twitch.tv\/videos\/533518741","video_id":"533518741","video_type":"twitch","unit":"Round","format":null,"note":null,"added":"9th, January 2020","other_links":null,"achieved":"15","player1":{"id":"20160","name":"SMH132","flag":"england","cheater":"0","banned":"0","url":"\/players\/U01IMTMy\/","staff_role":null,"staff_enabled":null,"staff_hidden":null}},{"players":1,"id":"55976","platform":"xb1","main_video":"https:\/\/www.twitch.tv\/videos\/634346906","video_id":"634346906","video_type":"twitch","unit":"Round","format":null,"note":null,"added":"28th, May 2020","other_links":null,"achieved":"15","player1":{"id":"920579","name":"Infinetlly","flag":"australia","cheater":"0","banned":"0","url":"\/players\/SW5maW5ldGxseQ\/","staff_role":null,"staff_enabled":null,"staff_hidden":null}},{"players":1,"id":"56566","platform":"ps4","main_video":"https:\/\/www.youtube.com\/watch?v=KQAuo_6n9sA&t=26s","video_id":"KQAuo_6n9sA","video_type":"youtube","unit":"Round","format":null,"note":null,"added":"4th, June 2020","other_links":null,"achieved":"15","player1":{"id":"920816","name":"Troolface07","flag":"portugal","cheater":"0","banned":"0","url":"\/players\/VHJvb2xmYWNlMDc\/","staff_role":null,"staff_enabled":null,"staff_hidden":null}},{"players":1,"id":"57543","platform":"ps4","main_video":"https:\/\/youtu.be\/xoitd4761jM","video_id":"xoitd4761jM","video_type":"youtube","unit":"Round","format":null,"note":null,"added":"14th, June 2020","other_links":null,"achieved":"15","player1":{"id":"921195","name":"FMars30","flag":"usa","cheater":"0","banned":"0","url":"\/players\/Rk1hcnMzMA\/","staff_role":null,"staff_enabled":null,"staff_hidden":null}},{"players":1,"id":"58207","platform":"xb1","main_video":"https:\/\/www.twitch.tv\/videos\/660435962","video_id":"660435962","video_type":"twitch","unit":"Round","format":null,"note":null,"added":"25th, June 2020","other_links":null,"achieved":"15","player1":{"id":"921626","name":"MarkwithnoH","flag":"usa","cheater":"0","banned":"0","url":"\/players\/TWFya3dpdGhub0g\/","staff_role":null,"staff_enabled":null,"staff_hidden":null}},{"players":1,"id":"64129","platform":"pc","main_video":"https:\/\/www.youtube.com\/watch?v=v3W4xxeiRg0","video_id":"v3W4xxeiRg0","video_type":"youtube","unit":"Round","format":null,"note":null,"added":"27th, September 2020","other_links":null,"achieved":"15","player1":{"id":"923910","name":"jao_neves06","flag":"brazil","cheater":"0","banned":"0","url":"\/players\/amFvX25ldmVzMDY\/","staff_role":null,"staff_enabled":null,"staff_hidden":null}},{"players":1,"id":"75419","platform":"xb1","main_video":"https:\/\/www.twitch.tv\/videos\/1110747869","video_id":"1110747869","video_type":"twitch","unit":"Round","format":null,"note":null,"added":"7th, August 2021","other_links":null,"achieved":"15","player1":{"id":"925506","name":"Chimyex","flag":"usa","cheater":"0","banned":"0","url":"\/players\/Q2hpbXlleA\/","staff_role":null,"staff_enabled":null,"staff_hidden":null}},{"players":1,"id":"80567","platform":"xb1","main_video":"https:\/\/www.twitch.tv\/videos\/1209148571","video_id":"1209148571","video_type":"twitch","unit":"Round","format":null,"note":null,"added":"18th, November 2021","other_links":null,"achieved":"15","player1":{"id":"1544427","name":"REYLO WALKER","flag":"usa","cheater":"0","banned":"0","url":"\/players\/UkVZTE8gV0FMS0VS\/","staff_role":null,"staff_enabled":null,"staff_hidden":null}}],"13":[{"players":1,"id":"41799","platform":"xb1","main_video":"https:\/\/www.twitch.tv\/videos\/497892964","video_id":"497892964","video_type":"twitch","unit":"Round","format":null,"note":null,"added":"22nd, October 2019","other_links":null,"achieved":"14","player1":{"id":"16584","name":"Sh0rtKing","flag":"usa","cheater":"0","banned":"0","url":"\/players\/U2gwcnRLaW5n\/","staff_role":null,"staff_enabled":null,"staff_hidden":null},"rank":13},{"players":1,"id":"47853","platform":"ps4","main_video":"https:\/\/youtu.be\/8rULfv-jE_c","video_id":"8rULfv-jE_c","video_type":"youtube","unit":"Round","format":null,"note":null,"added":"12th, March 2020","other_links":null,"achieved":"14","player1":{"id":"20642","name":"rennebu2","flag":"norway","cheater":"0","banned":"0","url":"\/players\/cmVubmVidTI\/","staff_role":null,"staff_enabled":null,"staff_hidden":null}},{"players":1,"id":"61841","platform":"ps4","main_video":"https:\/\/youtu.be\/E5FffBtuozU","video_id":"E5FffBtuozU","video_type":"youtube","unit":"Round","format":null,"note":null,"added":"14th, August 2020","other_links":null,"achieved":"14","player1":{"id":"923050","name":"Cobey177","flag":"england","cheater":"0","banned":"0","url":"\/players\/Q29iZXkxNzc\/","staff_role":null,"staff_enabled":null,"staff_hidden":null}},{"players":1,"id":"109866","platform":"pc","main_video":"https:\/\/youtu.be\/O9ZNnCc-Vsc","video_id":"O9ZNnCc-Vsc","video_type":"youtube","unit":"Round","format":null,"note":null,"added":"15th, August 2023","other_links":null,"achieved":"14","player1":{"id":"1553332","name":"tmp3","flag":"pakistan","cheater":"0","banned":"0","url":"\/players\/dG1wMw\/","staff_role":null,"staff_enabled":null,"staff_hidden":null}}],"14":[{"players":1,"id":"43217","platform":"ps4","main_video":"https:\/\/youtu.be\/Hl6_QkDCoJQ","video_id":"Hl6_QkDCoJQ","video_type":"youtube","unit":"Round","format":null,"note":null,"added":"30th, November 2019","other_links":null,"achieved":"13","player1":{"id":"19722","name":"LegitCamper67","flag":"mexico","cheater":"0","banned":"0","url":"\/players\/TGVnaXRDYW1wZXI2Nw\/","staff_role":null,"staff_enabled":null,"staff_hidden":null},"rank":14},{"players":1,"id":"55161","platform":"ps4","main_video":"https:\/\/youtu.be\/9w5vn2wSD9U","video_id":"9w5vn2wSD9U","video_type":"youtube","unit":"Round","format":null,"note":null,"added":"20th, May 2020","other_links":null,"achieved":"13","player1":{"id":"920007","name":"matteomazza27","flag":"italy","cheater":"0","banned":"0","url":"\/players\/bWF0dGVvbWF6emEyNw\/","staff_role":null,"staff_enabled":null,"staff_hidden":null}},{"players":1,"id":"56370","platform":"ps4","main_video":"https:\/\/www.twitch.tv\/videos\/638571560","video_id":"638571560","video_type":"twitch","unit":"Round","format":null,"note":null,"added":"1st, June 2020","other_links":null,"achieved":"13","player1":{"id":"16829","name":"Jason Hoisington","flag":"usa","cheater":"0","banned":"0","url":"\/players\/SmFzb24gSG9pc2luZ3Rvbg\/","staff_role":null,"staff_enabled":null,"staff_hidden":null}},{"players":1,"id":"58093","platform":"ps4","main_video":"https:\/\/www.youtube.com\/watch?v=K6dJ5XMTldA&feature=youtu.be","video_id":"K6dJ5XMTldA","video_type":"youtube","unit":"Round","format":null,"note":null,"added":"20th, June 2020","other_links":null,"achieved":"13","player1":{"id":"921534","name":"HDW Limitz","flag":"australia","cheater":"0","banned":"0","url":"\/players\/SERXIExpbWl0eg\/","staff_role":null,"staff_enabled":null,"staff_hidden":null}}],"15":[{"players":1,"id":"44133","platform":"xb1","main_video":"https:\/\/www.twitch.tv\/videos\/524812492","video_id":"524812492","video_type":"twitch","unit":"Round","format":null,"note":null,"added":"22nd, December 2019","other_links":null,"achieved":"12","player1":{"id":"19907","name":"xBionic Batx","flag":"canada","cheater":"0","banned":"0","url":"\/players\/eEJpb25pYyBCYXR4\/","staff_role":null,"staff_enabled":null,"staff_hidden":null},"rank":15},{"players":1,"id":"47581","platform":"ps4","main_video":"https:\/\/www.youtube.com\/watch?v=W5rdnqnVwjM","video_id":"W5rdnqnVwjM","video_type":"youtube","unit":"Round","format":null,"note":null,"added":"6th, March 2020","other_links":null,"achieved":"12","player1":{"id":"15731","name":"Midgetman0021","flag":"england","cheater":"0","banned":"0","url":"\/players\/TWlkZ2V0bWFuMDAyMQ\/","staff_role":null,"staff_enabled":null,"staff_hidden":null}}],"16":[{"players":1,"id":"49017","platform":"xb1","main_video":"https:\/\/www.youtube.com\/watch?v=_D_vXrCn0Gc&feature=youtu.be","video_id":"_D_vXrCn0Gc","video_type":"youtube","unit":"Round","format":null,"note":null,"added":"29th, March 2020","other_links":null,"achieved":"11","player1":{"id":"917576","name":"Davis Lyle","flag":"usa","cheater":"0","banned":"0","url":"\/players\/RGF2aXMgTHlsZQ\/","staff_role":null,"staff_enabled":null,"staff_hidden":null},"rank":16}]}