{"1":[{"players":3,"id":"110680","platform":"pc","main_video":"https:\/\/www.youtube.com\/watch?v=dm_EjZNiLvs","video_id":"dm_EjZNiLvs","video_type":"youtube","unit":"Round","format":null,"note":null,"added":"5th, September 2023","other_links":null,"achieved":"56","player1":{"id":"14321","name":"EXTREME","flag":"england","cheater":"0","banned":"0","url":"\/players\/RVhUUkVNRQ\/","staff_role":"Support Team","staff_enabled":"0","staff_hidden":"0"},"player2":{"id":"3230","name":"oJumpy","flag":"italy","cheater":"0","banned":"0","url":"\/players\/b0p1bXB5\/","staff_role":null,"staff_enabled":null,"staff_hidden":null},"player3":{"id":"1544087","name":"Square","flag":"england","cheater":"0","banned":"0","url":"\/players\/U3F1YXJl\/","staff_role":null,"staff_enabled":null,"staff_hidden":null},"rank":1}],"2":[{"players":3,"id":"105677","platform":"ps4","main_video":"https:\/\/www.twitch.tv\/videos\/1676191161","video_id":"1676191161","video_type":"twitch","unit":"Round","format":null,"note":null,"added":"19th, May 2023","other_links":null,"achieved":"53","player1":{"id":"1546593","name":"vorruckt","flag":"usa","cheater":"0","banned":"0","url":"\/players\/dm9ycnVja3Q\/","staff_role":null,"staff_enabled":null,"staff_hidden":null},"player2":{"id":"1549244","name":"RobbinRounds","flag":"usa","cheater":"0","banned":"0","url":"\/players\/Um9iYmluUm91bmRz\/","staff_role":null,"staff_enabled":null,"staff_hidden":null},"player3":{"id":"918619","name":"SpaghettiSouls28","flag":"canada","cheater":"0","banned":"0","url":"\/players\/U3BhZ2hldHRpU291bHMyOA\/","staff_role":null,"staff_enabled":null,"staff_hidden":null},"rank":2}],"3":[{"players":3,"id":"60055","platform":"ps4","main_video":"https:\/\/www.youtube.com\/watch?v=Fi2EWtK38Pg&feature=youtu.be","video_id":"Fi2EWtK38Pg","video_type":"youtube","unit":"Round","format":null,"note":null,"added":"15th, July 2020","other_links":["https:\/\/www.youtube.com\/watch?v=Dt3QWhR-57k&feature=youtu.be"],"achieved":"51","player1":{"id":"3006","name":"GizzyGao1","flag":"usa","cheater":"0","banned":"0","url":"\/players\/R2l6enlHYW8x\/","staff_role":null,"staff_enabled":null,"staff_hidden":null},"player2":{"id":"4649","name":"Captain Revolution","flag":"usa","cheater":"0","banned":"0","url":"\/players\/Q2FwdGFpbiBSZXZvbHV0aW9u\/","staff_role":null,"staff_enabled":null,"staff_hidden":null},"player3":{"id":"2874","name":"Spykes27","flag":"trinidad","cheater":"0","banned":"0","url":"\/players\/U3B5a2VzMjc\/","staff_role":null,"staff_enabled":null,"staff_hidden":null},"rank":3}],"4":[{"players":3,"id":"44941","platform":"xb1","main_video":"https:\/\/www.twitch.tv\/videos\/532218603","video_id":"532218603","video_type":"twitch","unit":"Round","format":null,"note":null,"added":"7th, January 2020","other_links":null,"achieved":"50","player1":{"id":"18816","name":"vDase","flag":"usa","cheater":"0","banned":"0","url":"\/players\/dkRhc2U\/","staff_role":null,"staff_enabled":null,"staff_hidden":null},"player2":{"id":"18614","name":"oSo Moisty","flag":"usa","cheater":"0","banned":"0","url":"\/players\/b1NvIE1vaXN0eQ\/","staff_role":null,"staff_enabled":null,"staff_hidden":null},"player3":{"id":"12282","name":"Dustyclips69","flag":"canada","cheater":"0","banned":"0","url":"\/players\/RHVzdHljbGlwczY5\/","staff_role":null,"staff_enabled":null,"staff_hidden":null},"rank":4}],"5":[{"players":3,"id":"42491","platform":"ps4","main_video":"https:\/\/www.twitch.tv\/videos\/505259159","video_id":"505259159","video_type":"twitch","unit":"Round","format":null,"note":null,"added":"9th, November 2019","other_links":["https:\/\/www.twitch.tv\/videos\/505259159"],"achieved":"35","player1":{"id":"19228","name":"Mr. DT","flag":"usa","cheater":"0","banned":"0","url":"\/players\/TXIuIERU\/","staff_role":null,"staff_enabled":null,"staff_hidden":null},"player2":{"id":"18020","name":"ImCappeee","flag":"sweden","cheater":"0","banned":"0","url":"\/players\/SW1DYXBwZWVl\/","staff_role":null,"staff_enabled":null,"staff_hidden":null},"player3":{"id":"18387","name":"TripOverThis420","flag":"usa","cheater":"0","banned":"0","url":"\/players\/VHJpcE92ZXJUaGlzNDIw\/","staff_role":null,"staff_enabled":null,"staff_hidden":null},"rank":5}],"6":[{"players":3,"id":"70684","platform":"ps4","main_video":"https:\/\/youtu.be\/3wJLY8-iBkI","video_id":"3wJLY8-iBkI","video_type":"youtube","unit":"Round","format":null,"note":null,"added":"21st, May 2021","other_links":["https:\/\/youtu.be\/HWY65js4D6Qhttps:\/\/youtu.be\/HWY65js4D6Q"],"achieved":"30","player1":{"id":"926140","name":"SHlNNNO","flag":"france","cheater":"0","banned":"0","url":"\/players\/U0hsTk5OTw\/","staff_role":null,"staff_enabled":null,"staff_hidden":null},"player2":{"id":"926141","name":"Januzdio_","flag":"france","cheater":"0","banned":"0","url":"\/players\/SmFudXpkaW9f\/","staff_role":null,"staff_enabled":null,"staff_hidden":null},"player3":{"id":"926142","name":"Quorena_","flag":"france","cheater":"0","banned":"0","url":"\/players\/UXVvcmVuYV8\/","staff_role":null,"staff_enabled":null,"staff_hidden":null},"rank":6}]}