{"1":[{"players":1,"id":"111236","platform":"ps4","main_video":"https:\/\/www.twitch.tv\/videos\/1929565982","video_id":"1929565982","video_type":"twitch","unit":"Round","format":null,"note":null,"added":"19th, September 2023","other_links":null,"achieved":"113","player1":{"id":"1552654","name":"DDxmsey-","flag":"germany","cheater":"0","banned":"0","url":"\/players\/RER4bXNleS0\/","staff_role":null,"staff_enabled":null,"staff_hidden":null},"rank":1}],"2":[{"players":1,"id":"103758","platform":"ps4","main_video":"https:\/\/youtu.be\/TwnZghylpUo","video_id":"TwnZghylpUo","video_type":"youtube","unit":"Round","format":null,"note":null,"added":"25th, April 2023","other_links":["https:\/\/youtu.be\/pYzT53KR4Kg"],"achieved":"112","player1":{"id":"1550981","name":"Stuggiiii","flag":"germany","cheater":"0","banned":"0","url":"\/players\/U3R1Z2dpaWlp\/","staff_role":null,"staff_enabled":null,"staff_hidden":null},"rank":2}],"3":[{"players":1,"id":"82857","platform":"ps4","main_video":"https:\/\/www.twitch.tv\/videos\/1259826573","video_id":"1259826573","video_type":"twitch","unit":"Round","format":null,"note":null,"added":"11th, January 2022","other_links":["https:\/\/www.twitch.tv\/videos\/1259835055","https:\/\/www.twitch.tv\/videos\/1259848545"],"achieved":"105","player1":{"id":"3439","name":"DonSchillaci86","flag":"italy","cheater":"0","banned":"0","url":"\/players\/RG9uU2NoaWxsYWNpODY\/","staff_role":null,"staff_enabled":null,"staff_hidden":null},"rank":3}],"4":[{"players":1,"id":"89001","platform":"ps4","main_video":"https:\/\/youtu.be\/S3IbePo13q8","video_id":"S3IbePo13q8","video_type":"youtube","unit":"Round","format":null,"note":null,"added":"5th, May 2022","other_links":null,"achieved":"93","player1":{"id":"1547524","name":"DaBigDaddyFish","flag":"usa","cheater":"0","banned":"0","url":"\/players\/RGFCaWdEYWRkeUZpc2g\/","staff_role":null,"staff_enabled":null,"staff_hidden":null},"rank":4}],"5":[{"players":1,"id":"64635","platform":"ps4","main_video":"https:\/\/www.twitch.tv\/videos\/761920372","video_id":"761920372","video_type":"twitch","unit":"Round","format":null,"note":null,"added":"6th, October 2020","other_links":null,"achieved":"85","player1":{"id":"922355","name":"Ace_fetty","flag":"usa","cheater":"0","banned":"0","url":"\/players\/QWNlX2ZldHR5\/","staff_role":null,"staff_enabled":null,"staff_hidden":null},"rank":5}],"6":[{"players":1,"id":"107180","platform":"xb1","main_video":"https:\/\/www.twitch.tv\/videos\/1850574002","video_id":"1850574002","video_type":"twitch","unit":"Round","format":null,"note":null,"added":"19th, June 2023","other_links":["https:\/\/www.twitch.tv\/videos\/1850311394"],"achieved":"81","player1":{"id":"1550330","name":"AmericanReptile","flag":"usa","cheater":"0","banned":"0","url":"\/players\/QW1lcmljYW5SZXB0aWxl\/","staff_role":null,"staff_enabled":null,"staff_hidden":null},"rank":6}],"7":[{"players":1,"id":"57792","platform":"xb1","main_video":"https:\/\/youtu.be\/o-F9hGaPW_I","video_id":"o-F9hGaPW_I","video_type":"youtube","unit":"Round","format":null,"note":null,"added":"19th, June 2020","other_links":null,"achieved":"80","player1":{"id":"13192","name":"Gravitypulls19","flag":"usa","cheater":"0","banned":"0","url":"\/players\/R3Jhdml0eXB1bGxzMTk\/","staff_role":null,"staff_enabled":null,"staff_hidden":null},"rank":7}],"8":[{"players":1,"id":"42425","platform":"ps4","main_video":"https:\/\/www.youtube.com\/watch?v=AjtiomrJbbE","video_id":"AjtiomrJbbE","video_type":"youtube","unit":"Round","format":null,"note":null,"added":"7th, November 2019","other_links":null,"achieved":"65","player1":{"id":"9129","name":"TheLonelyLegend","flag":"usa","cheater":"0","banned":"0","url":"\/players\/VGhlTG9uZWx5TGVnZW5k\/","staff_role":null,"staff_enabled":null,"staff_hidden":null},"rank":8}],"9":[{"players":1,"id":"61611","platform":"pc","main_video":"https:\/\/www.twitch.tv\/videos\/1261123038","video_id":"1261123038","video_type":"twitch","unit":"Round","format":null,"note":null,"added":"14th, January 2022","other_links":null,"achieved":"62","player1":{"id":"923087","name":"AceBomaye","flag":"usa","cheater":"0","banned":"0","url":"\/players\/QWNlQm9tYXll\/","staff_role":null,"staff_enabled":null,"staff_hidden":null},"rank":9}],"10":[{"players":1,"id":"45509","platform":"ps4","main_video":"https:\/\/youtu.be\/kGR4aSjAGHg","video_id":"kGR4aSjAGHg","video_type":"youtube","unit":"Round","format":null,"note":null,"added":"21st, January 2020","other_links":null,"achieved":"53","player1":{"id":"20315","name":"ColdBloodFTW","flag":"canada","cheater":"0","banned":"0","url":"\/players\/Q29sZEJsb29kRlRX\/","staff_role":null,"staff_enabled":null,"staff_hidden":null},"rank":10}],"11":[{"players":1,"id":"102168","platform":"ps4","main_video":"https:\/\/www.twitch.tv\/videos\/1482207584?filter=highlights&sort=time","video_id":"1482207584","video_type":"twitch","unit":"Round","format":null,"note":null,"added":"12th, March 2023","other_links":null,"achieved":"52","player1":{"id":"923338","name":"RedactedGamertag","flag":"usa","cheater":"0","banned":"0","url":"\/players\/UmVkYWN0ZWRHYW1lcnRhZw\/","staff_role":null,"staff_enabled":null,"staff_hidden":null},"rank":11}],"12":[{"players":1,"id":"57801","platform":"pc","main_video":"https:\/\/www.twitch.tv\/videos\/653092529","video_id":"653092529","video_type":"twitch","unit":"Round","format":null,"note":null,"added":"17th, June 2020","other_links":null,"achieved":"51","player1":{"id":"921441","name":"HellriserOfficial","flag":"usa","cheater":"0","banned":"0","url":"\/players\/SGVsbHJpc2VyT2ZmaWNpYWw\/","staff_role":null,"staff_enabled":null,"staff_hidden":null},"rank":12}],"13":[{"players":1,"id":"79554","platform":"ps4","main_video":"https:\/\/youtu.be\/ToK-17yI_zg","video_id":"ToK-17yI_zg","video_type":"youtube","unit":"Round","format":null,"note":null,"added":"30th, October 2021","other_links":null,"achieved":"50","player1":{"id":"1544678","name":"fear_no_man_0","flag":"usa","cheater":"0","banned":"0","url":"\/players\/ZmVhcl9ub19tYW5fMA\/","staff_role":null,"staff_enabled":null,"staff_hidden":null},"rank":13}],"14":[{"players":1,"id":"63468","platform":"pc","main_video":"https:\/\/www.youtube.com\/watch?v=OFZNegMhHR0&feature=youtu.be","video_id":"OFZNegMhHR0","video_type":"youtube","unit":"Round","format":null,"note":null,"added":"14th, September 2020","other_links":null,"achieved":"46","player1":{"id":"920567","name":"Jc Productions","flag":"usa","cheater":"0","banned":"0","url":"\/players\/SmMgUHJvZHVjdGlvbnM\/","staff_role":null,"staff_enabled":null,"staff_hidden":null},"rank":14},{"players":1,"id":"108157","platform":"pc","main_video":"https:\/\/www.youtube.com\/watch?v=SLN9JFdq07w&ab_channel=IAMASURGEON","video_id":"SLN9JFdq07w","video_type":"youtube","unit":"Round","format":null,"note":null,"added":"9th, July 2023","other_links":null,"achieved":"46","player1":{"id":"1552310","name":"I AM A SURGEON","flag":"qb","cheater":"0","banned":"0","url":"\/players\/SSBBTSBBIFNVUkdFT04\/","staff_role":null,"staff_enabled":null,"staff_hidden":null}}],"15":[{"players":1,"id":"61307","platform":"ps4","main_video":"https:\/\/m.youtube.com\/watch?v=aWot9tM-oyE","video_id":"aWot9tM-oyE","video_type":"youtube","unit":"Round","format":null,"note":null,"added":"3rd, August 2020","other_links":null,"achieved":"45","player1":{"id":"14983","name":"Mattociano","flag":"italy","cheater":"0","banned":"0","url":"\/players\/TWF0dG9jaWFubw\/","staff_role":null,"staff_enabled":null,"staff_hidden":null},"rank":15}],"16":[{"players":1,"id":"60996","platform":"xb1","main_video":"https:\/\/www.youtube.com\/watch?v=MrZu68Av53s","video_id":"MrZu68Av53s","video_type":"youtube","unit":"Round","format":null,"note":null,"added":"29th, July 2020","other_links":null,"achieved":"42","player1":{"id":"918965","name":"NicZombies","flag":"usa","cheater":"0","banned":"0","url":"\/players\/TmljWm9tYmllcw\/","staff_role":null,"staff_enabled":null,"staff_hidden":null},"rank":16}],"17":[{"players":1,"id":"57999","platform":"xb1","main_video":"https:\/\/www.twitch.tv\/videos\/655163297","video_id":"655163297","video_type":"twitch","unit":"Round","format":null,"note":null,"added":"19th, June 2020","other_links":null,"achieved":"40","player1":{"id":"920355","name":"FarawayEel562","flag":"usa","cheater":"0","banned":"0","url":"\/players\/RmFyYXdheUVlbDU2Mg\/","staff_role":null,"staff_enabled":null,"staff_hidden":null},"rank":17}],"18":[{"players":1,"id":"53218","platform":"ps4","main_video":"https:\/\/youtu.be\/wWVYmtUYaEA","video_id":"wWVYmtUYaEA","video_type":"youtube","unit":"Round","format":null,"note":null,"added":"8th, May 2020","other_links":null,"achieved":"39","player1":{"id":"919034","name":"Im_ShadyOz","flag":"australia","cheater":"0","banned":"0","url":"\/players\/SW1fU2hhZHlPeg\/","staff_role":null,"staff_enabled":null,"staff_hidden":null},"rank":18}],"19":[{"players":1,"id":"57827","platform":"xb1","main_video":"https:\/\/www.twitch.tv\/videos\/653181002","video_id":"653181002","video_type":"twitch","unit":"Round","format":null,"note":null,"added":"17th, June 2020","other_links":null,"achieved":"38","player1":{"id":"919831","name":"Parab1e","flag":"usa","cheater":"0","banned":"0","url":"\/players\/UGFyYWIxZQ\/","staff_role":null,"staff_enabled":null,"staff_hidden":null},"rank":19}],"20":[{"players":1,"id":"56683","platform":"xb1","main_video":"https:\/\/www.twitch.tv\/videos\/642187650","video_id":"642187650","video_type":"twitch","unit":"Round","format":null,"note":null,"added":"5th, June 2020","other_links":null,"achieved":"37","player1":{"id":"920862","name":"Noliver77","flag":"usa","cheater":"0","banned":"0","url":"\/players\/Tm9saXZlcjc3\/","staff_role":null,"staff_enabled":null,"staff_hidden":null},"rank":20}],"21":[{"players":1,"id":"47886","platform":"ps4","main_video":"https:\/\/youtu.be\/9qHEoBMo-H4","video_id":"9qHEoBMo-H4","video_type":"youtube","unit":"Round","format":null,"note":null,"added":"13th, March 2020","other_links":null,"achieved":"34","player1":{"id":"20642","name":"rennebu2","flag":"norway","cheater":"0","banned":"0","url":"\/players\/cmVubmVidTI\/","staff_role":null,"staff_enabled":null,"staff_hidden":null},"rank":21},{"players":1,"id":"53492","platform":"xb1","main_video":"https:\/\/www.twitch.tv\/videos\/616907835","video_id":"616907835","video_type":"twitch","unit":"Round","format":null,"note":null,"added":"10th, May 2020","other_links":null,"achieved":"34","player1":{"id":"919675","name":"BiPolar mos","flag":"usa","cheater":"0","banned":"0","url":"\/players\/QmlQb2xhciBtb3M\/","staff_role":null,"staff_enabled":null,"staff_hidden":null}},{"players":1,"id":"53862","platform":"xb1","main_video":"https:\/\/www.youtube.com\/watch?v=StmUl-UJ1LE","video_id":"StmUl-UJ1LE","video_type":"youtube","unit":"Round","format":null,"note":null,"added":"12th, May 2020","other_links":null,"achieved":"34","player1":{"id":"919639","name":"Joking Rage","flag":"usa","cheater":"0","banned":"0","url":"\/players\/Sm9raW5nIFJhZ2U\/","staff_role":null,"staff_enabled":null,"staff_hidden":null}}],"22":[{"players":1,"id":"57104","platform":"ps4","main_video":"https:\/\/www.twitch.tv\/videos\/646221525","video_id":"646221525","video_type":"twitch","unit":"Round","format":null,"note":null,"added":"9th, June 2020","other_links":null,"achieved":"32","player1":{"id":"16829","name":"Jason Hoisington","flag":"usa","cheater":"0","banned":"0","url":"\/players\/SmFzb24gSG9pc2luZ3Rvbg\/","staff_role":null,"staff_enabled":null,"staff_hidden":null},"rank":22}],"23":[{"players":1,"id":"85812","platform":"pc","main_video":"https:\/\/www.youtube.com\/watch?v=BoYBVDiZ97g&ab_channel=PepeHobo","video_id":"BoYBVDiZ97g","video_type":"youtube","unit":"Round","format":null,"note":null,"added":"10th, March 2022","other_links":null,"achieved":"30","player1":{"id":"925187","name":"Mr. HoboGuy","flag":"england","cheater":"0","banned":"0","url":"\/players\/TXIuIEhvYm9HdXk\/","staff_role":null,"staff_enabled":null,"staff_hidden":null},"rank":23}],"24":[{"players":1,"id":"54785","platform":"ps4","main_video":"https:\/\/youtu.be\/rB25opz--a8","video_id":"rB25opz--a8","video_type":"youtube","unit":"Round","format":null,"note":null,"added":"18th, May 2020","other_links":null,"achieved":"21","player1":{"id":"920142","name":"mattjohn01","flag":"usa","cheater":"0","banned":"0","url":"\/players\/bWF0dGpvaG4wMQ\/","staff_role":null,"staff_enabled":null,"staff_hidden":null},"rank":24}],"25":[{"players":1,"id":"108444","platform":"pc","main_video":"https:\/\/www.twitch.tv\/videos\/1871312081","video_id":"1871312081","video_type":"twitch","unit":"Round","format":null,"note":null,"added":"14th, July 2023","other_links":null,"achieved":"10","player1":{"id":"926551","name":"LxVer","flag":"ar","cheater":"0","banned":"0","url":"\/players\/THhWZXI\/","staff_role":null,"staff_enabled":null,"staff_hidden":null},"rank":25}]}