{"1":[{"players":2,"id":"95319","platform":"xb1","main_video":"https:\/\/youtu.be\/Coj6MYarL0s","video_id":"Coj6MYarL0s","video_type":"youtube","unit":"Time","format":"timestamp","note":null,"added":"2nd, September 2022","other_links":null,"achieved":"1:39","player1":{"id":"12207","name":"Rebirthh","flag":"usa","cheater":"0","banned":"0","url":"\/players\/UmViaXJ0aGg\/","staff_role":null,"staff_enabled":null,"staff_hidden":null},"player2":{"id":"20581","name":"Yolo Knifer 24","flag":"canada","cheater":"0","banned":"0","url":"\/players\/WW9sbyBLbmlmZXIgMjQ\/","staff_role":"Administrator","staff_enabled":"0","staff_hidden":"0"},"rank":1}]}