{"1":[{"players":2,"id":"107495","platform":"pc","main_video":"https:\/\/youtu.be\/PrUr1LEKCbQ","video_id":"PrUr1LEKCbQ","video_type":"youtube","unit":"Time","format":null,"note":null,"added":"27th, June 2023","other_links":["https:\/\/youtu.be\/9CboeQ8Xgiw"],"achieved":"2:51:09","player1":{"id":"1548532","name":"Pastekito","flag":"france","cheater":"0","banned":"0","url":"\/players\/UGFzdGVraXRv\/","staff_role":"Support Team","staff_enabled":"0","staff_hidden":"0"},"player2":{"id":"3956","name":"zTi_Eight","flag":"france","cheater":"0","banned":"0","url":"\/players\/elRpX0VpZ2h0\/","staff_role":null,"staff_enabled":null,"staff_hidden":null},"rank":1}],"2":[{"players":2,"id":"101540","platform":"xb1","main_video":"https:\/\/youtu.be\/nn1nBnp8TkE","video_id":"nn1nBnp8TkE","video_type":"youtube","unit":"Time","format":null,"note":null,"added":"27th, February 2023","other_links":null,"achieved":"3:26:36","player1":{"id":"918665","name":"Alahert","flag":"italy","cheater":"0","banned":"0","url":"\/players\/QWxhaGVydA\/","staff_role":null,"staff_enabled":null,"staff_hidden":null},"player2":{"id":"918962","name":"CannoneZeus99","flag":"italy","cheater":"0","banned":"0","url":"\/players\/Q2Fubm9uZVpldXM5OQ\/","staff_role":null,"staff_enabled":null,"staff_hidden":null},"rank":2}]}